{
  "m_GameObject": {
    "m_FileID": 0,
    "m_PathID": 0
  },
  "m_Enabled": 1,
  "m_Script": {
    "m_FileID": 0,
    "m_PathID": -2175866510260751636
  },
  "m_Name": "entries_100012",
  "m_stageId": 100012,
  "m_entries": [
    {
      "m_entryId": 1,
      "m_startTime": 0,
      "m_autoBoot": 1,
      "m_event": {
        "m_events": []
      },
      "m_deploy": {
        "m_deployments": [
          {
            "m_deployId": 1,
            "m_timing": 0,
            "m_routeId": 1,
            "m_params": [],
            "m_appId": 600226,
            "m_randomFlag": 0,
            "m_noNeedToDestroyFlag": 0,
            "m_dropItem": "",
            "m_entryId": 0,
            "m_omenType": 0,
            "m_bossFlag": 0,
            "m_appAnimFlag": 0,
            "m_appInvincibleFlag": 0,
            "m_battleEnd": 0
          },
          {
            "m_deployId": 2,
            "m_timing": 900,
            "m_routeId": 2,
            "m_params": [],
            "m_appId": 600226,
            "m_randomFlag": 0,
            "m_noNeedToDestroyFlag": 0,
            "m_dropItem": "",
            "m_entryId": 0,
            "m_omenType": 1,
            "m_bossFlag": 0,
            "m_appAnimFlag": 0,
            "m_appInvincibleFlag": 0,
            "m_battleEnd": 0
          }
        ]
      },
      "m_nextEntryId": 0,
      "m_callCount": 1
    },
    {
      "m_entryId": 2,
      "m_startTime": 0,
      "m_autoBoot": 1,
      "m_event": {
        "m_events": []
      },
      "m_deploy": {
        "m_deployments": [
          {
            "m_deployId": 1,
            "m_timing": 90,
            "m_routeId": 4,
            "m_params": [],
            "m_appId": 600229,
            "m_randomFlag": 0,
            "m_noNeedToDestroyFlag": 0,
            "m_dropItem": "",
            "m_entryId": 0,
            "m_omenType": 1,
            "m_bossFlag": 0,
            "m_appAnimFlag": 0,
            "m_appInvincibleFlag": 0,
            "m_battleEnd": 0
          },
          {
            "m_deployId": 2,
            "m_timing": 150,
            "m_routeId": 6,
            "m_params": [],
            "m_appId": 600229,
            "m_randomFlag": 0,
            "m_noNeedToDestroyFlag": 0,
            "m_dropItem": "",
            "m_entryId": 0,
            "m_omenType": 0,
            "m_bossFlag": 0,
            "m_appAnimFlag": 0,
            "m_appInvincibleFlag": 0,
            "m_battleEnd": 0
          },
          {
            "m_deployId": 3,
            "m_timing": 180,
            "m_routeId": 3,
            "m_params": [],
            "m_appId": 600229,
            "m_randomFlag": 0,
            "m_noNeedToDestroyFlag": 0,
            "m_dropItem": "",
            "m_entryId": 0,
            "m_omenType": 0,
            "m_bossFlag": 0,
            "m_appAnimFlag": 0,
            "m_appInvincibleFlag": 0,
            "m_battleEnd": 0
          },
          {
            "m_deployId": 4,
            "m_timing": 270,
            "m_routeId": 5,
            "m_params": [],
            "m_appId": 600229,
            "m_randomFlag": 0,
            "m_noNeedToDestroyFlag": 0,
            "m_dropItem": "",
            "m_entryId": 0,
            "m_omenType": 0,
            "m_bossFlag": 0,
            "m_appAnimFlag": 0,
            "m_appInvincibleFlag": 0,
            "m_battleEnd": 0
          },
          {
            "m_deployId": 5,
            "m_timing": 300,
            "m_routeId": 11,
            "m_params": [],
            "m_appId": 600229,
            "m_randomFlag": 0,
            "m_noNeedToDestroyFlag": 0,
            "m_dropItem": "",
            "m_entryId": 0,
            "m_omenType": 0,
            "m_bossFlag": 0,
            "m_appAnimFlag": 0,
            "m_appInvincibleFlag": 0,
            "m_battleEnd": 0
          },
          {
            "m_deployId": 6,
            "m_timing": 330,
            "m_routeId": 4,
            "m_params": [],
            "m_appId": 600229,
            "m_randomFlag": 0,
            "m_noNeedToDestroyFlag": 0,
            "m_dropItem": "",
            "m_entryId": 0,
            "m_omenType": 0,
            "m_bossFlag": 0,
            "m_appAnimFlag": 0,
            "m_appInvincibleFlag": 0,
            "m_battleEnd": 0
          },
          {
            "m_deployId": 7,
            "m_timing": 420,
            "m_routeId": 6,
            "m_params": [],
            "m_appId": 600229,
            "m_randomFlag": 0,
            "m_noNeedToDestroyFlag": 0,
            "m_dropItem": "",
            "m_entryId": 0,
            "m_omenType": 0,
            "m_bossFlag": 0,
            "m_appAnimFlag": 0,
            "m_appInvincibleFlag": 0,
            "m_battleEnd": 0
          },
          {
            "m_deployId": 8,
            "m_timing": 450,
            "m_routeId": 3,
            "m_params": [],
            "m_appId": 600229,
            "m_randomFlag": 0,
            "m_noNeedToDestroyFlag": 0,
            "m_dropItem": "",
            "m_entryId": 0,
            "m_omenType": 0,
            "m_bossFlag": 0,
            "m_appAnimFlag": 0,
            "m_appInvincibleFlag": 0,
            "m_battleEnd": 0
          },
          {
            "m_deployId": 9,
            "m_timing": 480,
            "m_routeId": 5,
            "m_params": [],
            "m_appId": 600229,
            "m_randomFlag": 0,
            "m_noNeedToDestroyFlag": 0,
            "m_dropItem": "",
            "m_entryId": 0,
            "m_omenType": 0,
            "m_bossFlag": 0,
            "m_appAnimFlag": 0,
            "m_appInvincibleFlag": 0,
            "m_battleEnd": 0
          },
          {
            "m_deployId": 10,
            "m_timing": 540,
            "m_routeId": 11,
            "m_params": [],
            "m_appId": 600229,
            "m_randomFlag": 0,
            "m_noNeedToDestroyFlag": 0,
            "m_dropItem": "",
            "m_entryId": 0,
            "m_omenType": 0,
            "m_bossFlag": 0,
            "m_appAnimFlag": 0,
            "m_appInvincibleFlag": 0,
            "m_battleEnd": 0
          },
          {
            "m_deployId": 11,
            "m_timing": 570,
            "m_routeId": 4,
            "m_params": [],
            "m_appId": 600229,
            "m_randomFlag": 0,
            "m_noNeedToDestroyFlag": 0,
            "m_dropItem": "",
            "m_entryId": 0,
            "m_omenType": 0,
            "m_bossFlag": 0,
            "m_appAnimFlag": 0,
            "m_appInvincibleFlag": 0,
            "m_battleEnd": 0
          },
          {
            "m_deployId": 12,
            "m_timing": 600,
            "m_routeId": 6,
            "m_params": [],
            "m_appId": 600229,
            "m_randomFlag": 0,
            "m_noNeedToDestroyFlag": 0,
            "m_dropItem": "",
            "m_entryId": 0,
            "m_omenType": 0,
            "m_bossFlag": 0,
            "m_appAnimFlag": 0,
            "m_appInvincibleFlag": 0,
            "m_battleEnd": 0
          },
          {
            "m_deployId": 13,
            "m_timing": 660,
            "m_routeId": 3,
            "m_params": [],
            "m_appId": 600229,
            "m_randomFlag": 0,
            "m_noNeedToDestroyFlag": 0,
            "m_dropItem": "",
            "m_entryId": 0,
            "m_omenType": 0,
            "m_bossFlag": 0,
            "m_appAnimFlag": 0,
            "m_appInvincibleFlag": 0,
            "m_battleEnd": 0
          },
          {
            "m_deployId": 14,
            "m_timing": 690,
            "m_routeId": 5,
            "m_params": [],
            "m_appId": 600229,
            "m_randomFlag": 0,
            "m_noNeedToDestroyFlag": 0,
            "m_dropItem": "",
            "m_entryId": 0,
            "m_omenType": 0,
            "m_bossFlag": 0,
            "m_appAnimFlag": 0,
            "m_appInvincibleFlag": 0,
            "m_battleEnd": 0
          },
          {
            "m_deployId": 15,
            "m_timing": 780,
            "m_routeId": 11,
            "m_params": [],
            "m_appId": 600229,
            "m_randomFlag": 0,
            "m_noNeedToDestroyFlag": 0,
            "m_dropItem": "",
            "m_entryId": 0,
            "m_omenType": 0,
            "m_bossFlag": 0,
            "m_appAnimFlag": 0,
            "m_appInvincibleFlag": 0,
            "m_battleEnd": 0
          }
        ]
      },
      "m_nextEntryId": 0,
      "m_callCount": 1
    },
    {
      "m_entryId": 3,
      "m_startTime": 0,
      "m_autoBoot": 1,
      "m_event": {
        "m_events": []
      },
      "m_deploy": {
        "m_deployments": [
          {
            "m_deployId": 1,
            "m_timing": 90,
            "m_routeId": 10,
            "m_params": [],
            "m_appId": 600229,
            "m_randomFlag": 0,
            "m_noNeedToDestroyFlag": 0,
            "m_dropItem": "",
            "m_entryId": 0,
            "m_omenType": 1,
            "m_bossFlag": 0,
            "m_appAnimFlag": 0,
            "m_appInvincibleFlag": 0,
            "m_battleEnd": 0
          },
          {
            "m_deployId": 2,
            "m_timing": 150,
            "m_routeId": 7,
            "m_params": [],
            "m_appId": 600229,
            "m_randomFlag": 0,
            "m_noNeedToDestroyFlag": 0,
            "m_dropItem": "",
            "m_entryId": 0,
            "m_omenType": 0,
            "m_bossFlag": 0,
            "m_appAnimFlag": 0,
            "m_appInvincibleFlag": 0,
            "m_battleEnd": 0
          },
          {
            "m_deployId": 3,
            "m_timing": 180,
            "m_routeId": 9,
            "m_params": [],
            "m_appId": 600229,
            "m_randomFlag": 0,
            "m_noNeedToDestroyFlag": 0,
            "m_dropItem": "",
            "m_entryId": 0,
            "m_omenType": 0,
            "m_bossFlag": 0,
            "m_appAnimFlag": 0,
            "m_appInvincibleFlag": 0,
            "m_battleEnd": 0
          },
          {
            "m_deployId": 4,
            "m_timing": 270,
            "m_routeId": 8,
            "m_params": [],
            "m_appId": 600229,
            "m_randomFlag": 0,
            "m_noNeedToDestroyFlag": 0,
            "m_dropItem": "",
            "m_entryId": 0,
            "m_omenType": 0,
            "m_bossFlag": 0,
            "m_appAnimFlag": 0,
            "m_appInvincibleFlag": 0,
            "m_battleEnd": 0
          },
          {
            "m_deployId": 5,
            "m_timing": 300,
            "m_routeId": 12,
            "m_params": [],
            "m_appId": 600229,
            "m_randomFlag": 0,
            "m_noNeedToDestroyFlag": 0,
            "m_dropItem": "",
            "m_entryId": 0,
            "m_omenType": 0,
            "m_bossFlag": 0,
            "m_appAnimFlag": 0,
            "m_appInvincibleFlag": 0,
            "m_battleEnd": 0
          },
          {
            "m_deployId": 6,
            "m_timing": 330,
            "m_routeId": 10,
            "m_params": [],
            "m_appId": 600229,
            "m_randomFlag": 0,
            "m_noNeedToDestroyFlag": 0,
            "m_dropItem": "",
            "m_entryId": 0,
            "m_omenType": 0,
            "m_bossFlag": 0,
            "m_appAnimFlag": 0,
            "m_appInvincibleFlag": 0,
            "m_battleEnd": 0
          },
          {
            "m_deployId": 7,
            "m_timing": 420,
            "m_routeId": 7,
            "m_params": [],
            "m_appId": 600229,
            "m_randomFlag": 0,
            "m_noNeedToDestroyFlag": 0,
            "m_dropItem": "",
            "m_entryId": 0,
            "m_omenType": 0,
            "m_bossFlag": 0,
            "m_appAnimFlag": 0,
            "m_appInvincibleFlag": 0,
            "m_battleEnd": 0
          },
          {
            "m_deployId": 8,
            "m_timing": 450,
            "m_routeId": 9,
            "m_params": [],
            "m_appId": 600229,
            "m_randomFlag": 0,
            "m_noNeedToDestroyFlag": 0,
            "m_dropItem": "",
            "m_entryId": 0,
            "m_omenType": 0,
            "m_bossFlag": 0,
            "m_appAnimFlag": 0,
            "m_appInvincibleFlag": 0,
            "m_battleEnd": 0
          },
          {
            "m_deployId": 9,
            "m_timing": 510,
            "m_routeId": 8,
            "m_params": [],
            "m_appId": 600229,
            "m_randomFlag": 0,
            "m_noNeedToDestroyFlag": 0,
            "m_dropItem": "",
            "m_entryId": 0,
            "m_omenType": 0,
            "m_bossFlag": 0,
            "m_appAnimFlag": 0,
            "m_appInvincibleFlag": 0,
            "m_battleEnd": 0
          },
          {
            "m_deployId": 10,
            "m_timing": 570,
            "m_routeId": 12,
            "m_params": [],
            "m_appId": 600229,
            "m_randomFlag": 0,
            "m_noNeedToDestroyFlag": 0,
            "m_dropItem": "",
            "m_entryId": 0,
            "m_omenType": 0,
            "m_bossFlag": 0,
            "m_appAnimFlag": 0,
            "m_appInvincibleFlag": 0,
            "m_battleEnd": 0
          },
          {
            "m_deployId": 11,
            "m_timing": 600,
            "m_routeId": 9,
            "m_params": [],
            "m_appId": 600229,
            "m_randomFlag": 0,
            "m_noNeedToDestroyFlag": 0,
            "m_dropItem": "",
            "m_entryId": 0,
            "m_omenType": 0,
            "m_bossFlag": 0,
            "m_appAnimFlag": 0,
            "m_appInvincibleFlag": 0,
            "m_battleEnd": 0
          },
          {
            "m_deployId": 12,
            "m_timing": 630,
            "m_routeId": 12,
            "m_params": [],
            "m_appId": 600229,
            "m_randomFlag": 0,
            "m_noNeedToDestroyFlag": 0,
            "m_dropItem": "",
            "m_entryId": 0,
            "m_omenType": 0,
            "m_bossFlag": 0,
            "m_appAnimFlag": 0,
            "m_appInvincibleFlag": 0,
            "m_battleEnd": 0
          },
          {
            "m_deployId": 13,
            "m_timing": 690,
            "m_routeId": 8,
            "m_params": [],
            "m_appId": 600229,
            "m_randomFlag": 0,
            "m_noNeedToDestroyFlag": 0,
            "m_dropItem": "",
            "m_entryId": 0,
            "m_omenType": 0,
            "m_bossFlag": 0,
            "m_appAnimFlag": 0,
            "m_appInvincibleFlag": 0,
            "m_battleEnd": 0
          },
          {
            "m_deployId": 14,
            "m_timing": 750,
            "m_routeId": 7,
            "m_params": [],
            "m_appId": 600229,
            "m_randomFlag": 0,
            "m_noNeedToDestroyFlag": 0,
            "m_dropItem": "",
            "m_entryId": 0,
            "m_omenType": 0,
            "m_bossFlag": 0,
            "m_appAnimFlag": 0,
            "m_appInvincibleFlag": 0,
            "m_battleEnd": 0
          },
          {
            "m_deployId": 15,
            "m_timing": 780,
            "m_routeId": 10,
            "m_params": [],
            "m_appId": 600229,
            "m_randomFlag": 0,
            "m_noNeedToDestroyFlag": 0,
            "m_dropItem": "",
            "m_entryId": 0,
            "m_omenType": 0,
            "m_bossFlag": 0,
            "m_appAnimFlag": 0,
            "m_appInvincibleFlag": 0,
            "m_battleEnd": 0
          }
        ]
      },
      "m_nextEntryId": 0,
      "m_callCount": 1
    }
  ]
}