{
  "m_GameObject": {
    "m_FileID": 0,
    "m_PathID": 0
  },
  "m_Enabled": 1,
  "m_Script": {
    "m_FileID": 0,
    "m_PathID": -5871523156564247384
  },
  "m_Name": "routes_46002",
  "m_layoutId": 46002,
  "m_routes": [
    {
      "m_routeId": 1,
      "m_omenPos": {
        "x": 0.0,
        "y": 0.0
      },
      "m_points": [
        {
          "m_pos": {
            "x": 1343.953,
            "y": 381.15384
          },
          "m_tag": "",
          "m_warp": 0,
          "m_wait": 0,
          "m_speed_scale": 0,
          "m_activateEnemyNodeAbilityIds": [],
          "m_deactivateEnemyNodeAbilityIds": []
        },
        {
          "m_pos": {
            "x": 859.23083,
            "y": 383.07693
          },
          "m_tag": "",
          "m_warp": 0,
          "m_wait": 3000,
          "m_speed_scale": 0,
          "m_activateEnemyNodeAbilityIds": [],
          "m_deactivateEnemyNodeAbilityIds": []
        },
        {
          "m_pos": {
            "x": 573.0769,
            "y": 384.6154
          },
          "m_tag": "",
          "m_warp": 0,
          "m_wait": 1800,
          "m_speed_scale": 0,
          "m_activateEnemyNodeAbilityIds": [],
          "m_deactivateEnemyNodeAbilityIds": []
        },
        {
          "m_pos": {
            "x": -150.91882,
            "y": 383.5043
          },
          "m_tag": "",
          "m_warp": 0,
          "m_wait": 0,
          "m_speed_scale": 0,
          "m_activateEnemyNodeAbilityIds": [],
          "m_deactivateEnemyNodeAbilityIds": []
        }
      ]
    },
    {
      "m_routeId": 2,
      "m_omenPos": {
        "x": 0.0,
        "y": 0.0
      },
      "m_points": [
        {
          "m_pos": {
            "x": 1313.077,
            "y": 309.23074
          },
          "m_tag": "",
          "m_warp": 0,
          "m_wait": 0,
          "m_speed_scale": 0,
          "m_activateEnemyNodeAbilityIds": [],
          "m_deactivateEnemyNodeAbilityIds": []
        },
        {
          "m_pos": {
            "x": 1126.9231,
            "y": 309.23074
          },
          "m_tag": "",
          "m_warp": 0,
          "m_wait": 0,
          "m_speed_scale": 0,
          "m_activateEnemyNodeAbilityIds": [],
          "m_deactivateEnemyNodeAbilityIds": []
        },
        {
          "m_pos": {
            "x": -63.846207,
            "y": 316.92307
          },
          "m_tag": "",
          "m_warp": 0,
          "m_wait": 0,
          "m_speed_scale": 0,
          "m_activateEnemyNodeAbilityIds": [],
          "m_deactivateEnemyNodeAbilityIds": []
        }
      ]
    },
    {
      "m_routeId": 3,
      "m_omenPos": {
        "x": 0.0,
        "y": 0.0
      },
      "m_points": [
        {
          "m_pos": {
            "x": 1313.077,
            "y": 326.15384
          },
          "m_tag": "",
          "m_warp": 0,
          "m_wait": 0,
          "m_speed_scale": 0,
          "m_activateEnemyNodeAbilityIds": [],
          "m_deactivateEnemyNodeAbilityIds": []
        },
        {
          "m_pos": {
            "x": 1126.9231,
            "y": 326.15384
          },
          "m_tag": "",
          "m_warp": 0,
          "m_wait": 0,
          "m_speed_scale": 0,
          "m_activateEnemyNodeAbilityIds": [],
          "m_deactivateEnemyNodeAbilityIds": []
        },
        {
          "m_pos": {
            "x": -63.846207,
            "y": 333.8462
          },
          "m_tag": "",
          "m_warp": 0,
          "m_wait": 0,
          "m_speed_scale": 0,
          "m_activateEnemyNodeAbilityIds": [],
          "m_deactivateEnemyNodeAbilityIds": []
        }
      ]
    },
    {
      "m_routeId": 4,
      "m_omenPos": {
        "x": 0.0,
        "y": 0.0
      },
      "m_points": [
        {
          "m_pos": {
            "x": 1311.5387,
            "y": 343.07693
          },
          "m_tag": "",
          "m_warp": 0,
          "m_wait": 0,
          "m_speed_scale": 0,
          "m_activateEnemyNodeAbilityIds": [],
          "m_deactivateEnemyNodeAbilityIds": []
        },
        {
          "m_pos": {
            "x": 1125.3848,
            "y": 343.07693
          },
          "m_tag": "",
          "m_warp": 0,
          "m_wait": 0,
          "m_speed_scale": 0,
          "m_activateEnemyNodeAbilityIds": [],
          "m_deactivateEnemyNodeAbilityIds": []
        },
        {
          "m_pos": {
            "x": -65.38458,
            "y": 350.76926
          },
          "m_tag": "",
          "m_warp": 0,
          "m_wait": 0,
          "m_speed_scale": 0,
          "m_activateEnemyNodeAbilityIds": [],
          "m_deactivateEnemyNodeAbilityIds": []
        }
      ]
    },
    {
      "m_routeId": 5,
      "m_omenPos": {
        "x": 0.0,
        "y": 0.0
      },
      "m_points": [
        {
          "m_pos": {
            "x": 1303.8463,
            "y": 416.9231
          },
          "m_tag": "",
          "m_warp": 0,
          "m_wait": 0,
          "m_speed_scale": 0,
          "m_activateEnemyNodeAbilityIds": [],
          "m_deactivateEnemyNodeAbilityIds": []
        },
        {
          "m_pos": {
            "x": 1117.6924,
            "y": 416.9231
          },
          "m_tag": "",
          "m_warp": 0,
          "m_wait": 0,
          "m_speed_scale": 0,
          "m_activateEnemyNodeAbilityIds": [],
          "m_deactivateEnemyNodeAbilityIds": []
        },
        {
          "m_pos": {
            "x": -73.076965,
            "y": 424.6154
          },
          "m_tag": "",
          "m_warp": 0,
          "m_wait": 0,
          "m_speed_scale": 0,
          "m_activateEnemyNodeAbilityIds": [],
          "m_deactivateEnemyNodeAbilityIds": []
        }
      ]
    },
    {
      "m_routeId": 6,
      "m_omenPos": {
        "x": 0.0,
        "y": 0.0
      },
      "m_points": [
        {
          "m_pos": {
            "x": 1305.3848,
            "y": 433.84613
          },
          "m_tag": "",
          "m_warp": 0,
          "m_wait": 0,
          "m_speed_scale": 0,
          "m_activateEnemyNodeAbilityIds": [],
          "m_deactivateEnemyNodeAbilityIds": []
        },
        {
          "m_pos": {
            "x": 1119.2308,
            "y": 433.84613
          },
          "m_tag": "",
          "m_warp": 0,
          "m_wait": 0,
          "m_speed_scale": 0,
          "m_activateEnemyNodeAbilityIds": [],
          "m_deactivateEnemyNodeAbilityIds": []
        },
        {
          "m_pos": {
            "x": -71.5385,
            "y": 441.53842
          },
          "m_tag": "",
          "m_warp": 0,
          "m_wait": 0,
          "m_speed_scale": 0,
          "m_activateEnemyNodeAbilityIds": [],
          "m_deactivateEnemyNodeAbilityIds": []
        }
      ]
    },
    {
      "m_routeId": 7,
      "m_omenPos": {
        "x": 0.0,
        "y": 0.0
      },
      "m_points": [
        {
          "m_pos": {
            "x": 1305.3848,
            "y": 449.2308
          },
          "m_tag": "",
          "m_warp": 0,
          "m_wait": 0,
          "m_speed_scale": 0,
          "m_activateEnemyNodeAbilityIds": [],
          "m_deactivateEnemyNodeAbilityIds": []
        },
        {
          "m_pos": {
            "x": 1119.2308,
            "y": 449.2308
          },
          "m_tag": "",
          "m_warp": 0,
          "m_wait": 0,
          "m_speed_scale": 0,
          "m_activateEnemyNodeAbilityIds": [],
          "m_deactivateEnemyNodeAbilityIds": []
        },
        {
          "m_pos": {
            "x": -71.5385,
            "y": 456.9231
          },
          "m_tag": "",
          "m_warp": 0,
          "m_wait": 0,
          "m_speed_scale": 0,
          "m_activateEnemyNodeAbilityIds": [],
          "m_deactivateEnemyNodeAbilityIds": []
        }
      ]
    },
    {
      "m_routeId": 8,
      "m_omenPos": {
        "x": 0.0,
        "y": 0.0
      },
      "m_points": [
        {
          "m_pos": {
            "x": 1313.077,
            "y": 309.23074
          },
          "m_tag": "",
          "m_warp": 0,
          "m_wait": 0,
          "m_speed_scale": 0,
          "m_activateEnemyNodeAbilityIds": [],
          "m_deactivateEnemyNodeAbilityIds": []
        },
        {
          "m_pos": {
            "x": 1126.9231,
            "y": 309.23074
          },
          "m_tag": "",
          "m_warp": 0,
          "m_wait": 0,
          "m_speed_scale": 0,
          "m_activateEnemyNodeAbilityIds": [],
          "m_deactivateEnemyNodeAbilityIds": []
        },
        {
          "m_pos": {
            "x": 1022.01636,
            "y": 306.7319
          },
          "m_tag": "",
          "m_warp": 0,
          "m_wait": 0,
          "m_speed_scale": 0,
          "m_activateEnemyNodeAbilityIds": [],
          "m_deactivateEnemyNodeAbilityIds": []
        },
        {
          "m_pos": {
            "x": 936.47955,
            "y": 234.61261
          },
          "m_tag": "",
          "m_warp": 0,
          "m_wait": 0,
          "m_speed_scale": 0,
          "m_activateEnemyNodeAbilityIds": [],
          "m_deactivateEnemyNodeAbilityIds": []
        },
        {
          "m_pos": {
            "x": 871.06903,
            "y": 159.13896
          },
          "m_tag": "",
          "m_warp": 0,
          "m_wait": 0,
          "m_speed_scale": 0,
          "m_activateEnemyNodeAbilityIds": [],
          "m_deactivateEnemyNodeAbilityIds": []
        },
        {
          "m_pos": {
            "x": 797.6923,
            "y": 47.692253
          },
          "m_tag": "",
          "m_warp": 0,
          "m_wait": 0,
          "m_speed_scale": 0,
          "m_activateEnemyNodeAbilityIds": [],
          "m_deactivateEnemyNodeAbilityIds": []
        },
        {
          "m_pos": {
            "x": 755.3427,
            "y": -30.383778
          },
          "m_tag": "",
          "m_warp": 300,
          "m_wait": 0,
          "m_speed_scale": 0,
          "m_activateEnemyNodeAbilityIds": [],
          "m_deactivateEnemyNodeAbilityIds": []
        },
        {
          "m_pos": {
            "x": 549.0481,
            "y": -23.674917
          },
          "m_tag": "",
          "m_warp": 0,
          "m_wait": 0,
          "m_speed_scale": 0,
          "m_activateEnemyNodeAbilityIds": [],
          "m_deactivateEnemyNodeAbilityIds": []
        },
        {
          "m_pos": {
            "x": 503.76398,
            "y": 45.089912
          },
          "m_tag": "",
          "m_warp": 0,
          "m_wait": 0,
          "m_speed_scale": 0,
          "m_activateEnemyNodeAbilityIds": [],
          "m_deactivateEnemyNodeAbilityIds": []
        },
        {
          "m_pos": {
            "x": 448.41663,
            "y": 140.68985
          },
          "m_tag": "",
          "m_warp": 0,
          "m_wait": 0,
          "m_speed_scale": 0,
          "m_activateEnemyNodeAbilityIds": [],
          "m_deactivateEnemyNodeAbilityIds": []
        },
        {
          "m_pos": {
            "x": 404.80963,
            "y": 206.10037
          },
          "m_tag": "",
          "m_warp": 0,
          "m_wait": 0,
          "m_speed_scale": 0,
          "m_activateEnemyNodeAbilityIds": [],
          "m_deactivateEnemyNodeAbilityIds": []
        },
        {
          "m_pos": {
            "x": 351.13947,
            "y": 316.79504
          },
          "m_tag": "",
          "m_warp": 0,
          "m_wait": 0,
          "m_speed_scale": 0,
          "m_activateEnemyNodeAbilityIds": [],
          "m_deactivateEnemyNodeAbilityIds": []
        },
        {
          "m_pos": {
            "x": 277.34296,
            "y": 316.79504
          },
          "m_tag": "",
          "m_warp": 0,
          "m_wait": 0,
          "m_speed_scale": 0,
          "m_activateEnemyNodeAbilityIds": [],
          "m_deactivateEnemyNodeAbilityIds": []
        },
        {
          "m_pos": {
            "x": -63.12704,
            "y": 313.44064
          },
          "m_tag": "",
          "m_warp": 0,
          "m_wait": 0,
          "m_speed_scale": 0,
          "m_activateEnemyNodeAbilityIds": [],
          "m_deactivateEnemyNodeAbilityIds": []
        }
      ]
    },
    {
      "m_routeId": 9,
      "m_omenPos": {
        "x": 0.0,
        "y": 0.0
      },
      "m_points": [
        {
          "m_pos": {
            "x": 1313.077,
            "y": 326.15384
          },
          "m_tag": "",
          "m_warp": 0,
          "m_wait": 0,
          "m_speed_scale": 0,
          "m_activateEnemyNodeAbilityIds": [],
          "m_deactivateEnemyNodeAbilityIds": []
        },
        {
          "m_pos": {
            "x": 1126.9231,
            "y": 326.15384
          },
          "m_tag": "",
          "m_warp": 0,
          "m_wait": 0,
          "m_speed_scale": 0,
          "m_activateEnemyNodeAbilityIds": [],
          "m_deactivateEnemyNodeAbilityIds": []
        },
        {
          "m_pos": {
            "x": 1068.4617,
            "y": 326.15384
          },
          "m_tag": "",
          "m_warp": 0,
          "m_wait": 0,
          "m_speed_scale": 0,
          "m_activateEnemyNodeAbilityIds": [],
          "m_deactivateEnemyNodeAbilityIds": []
        },
        {
          "m_pos": {
            "x": 1011.95337,
            "y": 274.86523
          },
          "m_tag": "",
          "m_warp": 0,
          "m_wait": 0,
          "m_speed_scale": 0,
          "m_activateEnemyNodeAbilityIds": [],
          "m_deactivateEnemyNodeAbilityIds": []
        },
        {
          "m_pos": {
            "x": 956.60583,
            "y": 229.58102
          },
          "m_tag": "",
          "m_warp": 0,
          "m_wait": 0,
          "m_speed_scale": 0,
          "m_activateEnemyNodeAbilityIds": [],
          "m_deactivateEnemyNodeAbilityIds": []
        },
        {
          "m_pos": {
            "x": 899.58136,
            "y": 157.46179
          },
          "m_tag": "",
          "m_warp": 0,
          "m_wait": 0,
          "m_speed_scale": 0,
          "m_activateEnemyNodeAbilityIds": [],
          "m_deactivateEnemyNodeAbilityIds": []
        },
        {
          "m_pos": {
            "x": 825.78485,
            "y": 55.153084
          },
          "m_tag": "",
          "m_warp": 0,
          "m_wait": 0,
          "m_speed_scale": 0,
          "m_activateEnemyNodeAbilityIds": [],
          "m_deactivateEnemyNodeAbilityIds": []
        },
        {
          "m_pos": {
            "x": 785.5322,
            "y": -28.70655
          },
          "m_tag": "",
          "m_warp": 300,
          "m_wait": 0,
          "m_speed_scale": 0,
          "m_activateEnemyNodeAbilityIds": [],
          "m_deactivateEnemyNodeAbilityIds": []
        },
        {
          "m_pos": {
            "x": 525.56744,
            "y": -25.352192
          },
          "m_tag": "",
          "m_warp": 0,
          "m_wait": 0,
          "m_speed_scale": 0,
          "m_activateEnemyNodeAbilityIds": [],
          "m_deactivateEnemyNodeAbilityIds": []
        },
        {
          "m_pos": {
            "x": 481.96045,
            "y": 40.058327
          },
          "m_tag": "",
          "m_warp": 0,
          "m_wait": 0,
          "m_speed_scale": 0,
          "m_activateEnemyNodeAbilityIds": [],
          "m_deactivateEnemyNodeAbilityIds": []
        },
        {
          "m_pos": {
            "x": 424.9359,
            "y": 139.0127
          },
          "m_tag": "",
          "m_warp": 0,
          "m_wait": 0,
          "m_speed_scale": 0,
          "m_activateEnemyNodeAbilityIds": [],
          "m_deactivateEnemyNodeAbilityIds": []
        },
        {
          "m_pos": {
            "x": 381.32892,
            "y": 204.42317
          },
          "m_tag": "",
          "m_warp": 0,
          "m_wait": 0,
          "m_speed_scale": 0,
          "m_activateEnemyNodeAbilityIds": [],
          "m_deactivateEnemyNodeAbilityIds": []
        },
        {
          "m_pos": {
            "x": 331.01315,
            "y": 306.7319
          },
          "m_tag": "",
          "m_warp": 0,
          "m_wait": 0,
          "m_speed_scale": 0,
          "m_activateEnemyNodeAbilityIds": [],
          "m_deactivateEnemyNodeAbilityIds": []
        },
        {
          "m_pos": {
            "x": 302.50085,
            "y": 330.21255
          },
          "m_tag": "",
          "m_warp": 0,
          "m_wait": 0,
          "m_speed_scale": 0,
          "m_activateEnemyNodeAbilityIds": [],
          "m_deactivateEnemyNodeAbilityIds": []
        },
        {
          "m_pos": {
            "x": -61.44986,
            "y": 333.56696
          },
          "m_tag": "",
          "m_warp": 0,
          "m_wait": 0,
          "m_speed_scale": 0,
          "m_activateEnemyNodeAbilityIds": [],
          "m_deactivateEnemyNodeAbilityIds": []
        }
      ]
    },
    {
      "m_routeId": 10,
      "m_omenPos": {
        "x": 0.0,
        "y": 0.0
      },
      "m_points": [
        {
          "m_pos": {
            "x": 1311.5387,
            "y": 343.07693
          },
          "m_tag": "",
          "m_warp": 0,
          "m_wait": 0,
          "m_speed_scale": 0,
          "m_activateEnemyNodeAbilityIds": [],
          "m_deactivateEnemyNodeAbilityIds": []
        },
        {
          "m_pos": {
            "x": 1109.2302,
            "y": 341.95288
          },
          "m_tag": "",
          "m_warp": 0,
          "m_wait": 0,
          "m_speed_scale": 0,
          "m_activateEnemyNodeAbilityIds": [],
          "m_deactivateEnemyNodeAbilityIds": []
        },
        {
          "m_pos": {
            "x": 1035.434,
            "y": 264.80206
          },
          "m_tag": "",
          "m_warp": 0,
          "m_wait": 0,
          "m_speed_scale": 0,
          "m_activateEnemyNodeAbilityIds": [],
          "m_deactivateEnemyNodeAbilityIds": []
        },
        {
          "m_pos": {
            "x": 978.4093,
            "y": 221.19508
          },
          "m_tag": "",
          "m_warp": 0,
          "m_wait": 0,
          "m_speed_scale": 0,
          "m_activateEnemyNodeAbilityIds": [],
          "m_deactivateEnemyNodeAbilityIds": []
        },
        {
          "m_pos": {
            "x": 923.062,
            "y": 150.75302
          },
          "m_tag": "",
          "m_warp": 0,
          "m_wait": 0,
          "m_speed_scale": 0,
          "m_activateEnemyNodeAbilityIds": [],
          "m_deactivateEnemyNodeAbilityIds": []
        },
        {
          "m_pos": {
            "x": 847.5884,
            "y": 45.089912
          },
          "m_tag": "",
          "m_warp": 0,
          "m_wait": 0,
          "m_speed_scale": 0,
          "m_activateEnemyNodeAbilityIds": [],
          "m_deactivateEnemyNodeAbilityIds": []
        },
        {
          "m_pos": {
            "x": 810.6901,
            "y": -30.383778
          },
          "m_tag": "",
          "m_warp": 300,
          "m_wait": 0,
          "m_speed_scale": 0,
          "m_activateEnemyNodeAbilityIds": [],
          "m_deactivateEnemyNodeAbilityIds": []
        },
        {
          "m_pos": {
            "x": 493.70074,
            "y": -25.352192
          },
          "m_tag": "",
          "m_warp": 0,
          "m_wait": 0,
          "m_speed_scale": 0,
          "m_activateEnemyNodeAbilityIds": [],
          "m_deactivateEnemyNodeAbilityIds": []
        },
        {
          "m_pos": {
            "x": 461.8341,
            "y": 28.317928
          },
          "m_tag": "",
          "m_warp": 0,
          "m_wait": 0,
          "m_speed_scale": 0,
          "m_activateEnemyNodeAbilityIds": [],
          "m_deactivateEnemyNodeAbilityIds": []
        },
        {
          "m_pos": {
            "x": 401.45526,
            "y": 137.33545
          },
          "m_tag": "",
          "m_warp": 0,
          "m_wait": 0,
          "m_speed_scale": 0,
          "m_activateEnemyNodeAbilityIds": [],
          "m_deactivateEnemyNodeAbilityIds": []
        },
        {
          "m_pos": {
            "x": 357.84827,
            "y": 202.74596
          },
          "m_tag": "",
          "m_warp": 0,
          "m_wait": 0,
          "m_speed_scale": 0,
          "m_activateEnemyNodeAbilityIds": [],
          "m_deactivateEnemyNodeAbilityIds": []
        },
        {
          "m_pos": {
            "x": 314.24127,
            "y": 291.63715
          },
          "m_tag": "",
          "m_warp": 0,
          "m_wait": 0,
          "m_speed_scale": 0,
          "m_activateEnemyNodeAbilityIds": [],
          "m_deactivateEnemyNodeAbilityIds": []
        },
        {
          "m_pos": {
            "x": 287.4061,
            "y": 346.9845
          },
          "m_tag": "",
          "m_warp": 0,
          "m_wait": 0,
          "m_speed_scale": 0,
          "m_activateEnemyNodeAbilityIds": [],
          "m_deactivateEnemyNodeAbilityIds": []
        },
        {
          "m_pos": {
            "x": -61.44986,
            "y": 350.3389
          },
          "m_tag": "",
          "m_warp": 0,
          "m_wait": 0,
          "m_speed_scale": 0,
          "m_activateEnemyNodeAbilityIds": [],
          "m_deactivateEnemyNodeAbilityIds": []
        }
      ]
    },
    {
      "m_routeId": 11,
      "m_omenPos": {
        "x": 0.0,
        "y": 0.0
      },
      "m_points": [
        {
          "m_pos": {
            "x": 1303.8463,
            "y": 416.9231
          },
          "m_tag": "",
          "m_warp": 0,
          "m_wait": 0,
          "m_speed_scale": 0,
          "m_activateEnemyNodeAbilityIds": [],
          "m_deactivateEnemyNodeAbilityIds": []
        },
        {
          "m_pos": {
            "x": 1117.6924,
            "y": 416.9231
          },
          "m_tag": "",
          "m_warp": 0,
          "m_wait": 0,
          "m_speed_scale": 0,
          "m_activateEnemyNodeAbilityIds": [],
          "m_deactivateEnemyNodeAbilityIds": []
        },
        {
          "m_pos": {
            "x": 844.75336,
            "y": 418.41763
          },
          "m_tag": "",
          "m_warp": 0,
          "m_wait": 0,
          "m_speed_scale": 0,
          "m_activateEnemyNodeAbilityIds": [],
          "m_deactivateEnemyNodeAbilityIds": []
        },
        {
          "m_pos": {
            "x": 882.80945,
            "y": 516.3809
          },
          "m_tag": "",
          "m_warp": 0,
          "m_wait": 0,
          "m_speed_scale": 0,
          "m_activateEnemyNodeAbilityIds": [],
          "m_deactivateEnemyNodeAbilityIds": []
        },
        {
          "m_pos": {
            "x": 1012.54285,
            "y": 743.1197
          },
          "m_tag": "",
          "m_warp": 300,
          "m_wait": 0,
          "m_speed_scale": 0,
          "m_activateEnemyNodeAbilityIds": [],
          "m_deactivateEnemyNodeAbilityIds": []
        },
        {
          "m_pos": {
            "x": 577.7137,
            "y": 747.82056
          },
          "m_tag": "",
          "m_warp": 0,
          "m_wait": 0,
          "m_speed_scale": 0,
          "m_activateEnemyNodeAbilityIds": [],
          "m_deactivateEnemyNodeAbilityIds": []
        },
        {
          "m_pos": {
            "x": 516.60254,
            "y": 557.4359
          },
          "m_tag": "",
          "m_warp": 0,
          "m_wait": 0,
          "m_speed_scale": 0,
          "m_activateEnemyNodeAbilityIds": [],
          "m_deactivateEnemyNodeAbilityIds": []
        },
        {
          "m_pos": {
            "x": 469.06238,
            "y": 421.772
          },
          "m_tag": "",
          "m_warp": 0,
          "m_wait": 0,
          "m_speed_scale": 0,
          "m_activateEnemyNodeAbilityIds": [],
          "m_deactivateEnemyNodeAbilityIds": []
        },
        {
          "m_pos": {
            "x": -79.37956,
            "y": 425.12646
          },
          "m_tag": "",
          "m_warp": 0,
          "m_wait": 0,
          "m_speed_scale": 0,
          "m_activateEnemyNodeAbilityIds": [],
          "m_deactivateEnemyNodeAbilityIds": []
        }
      ]
    },
    {
      "m_routeId": 12,
      "m_omenPos": {
        "x": 0.0,
        "y": 0.0
      },
      "m_points": [
        {
          "m_pos": {
            "x": 1305.3848,
            "y": 433.84613
          },
          "m_tag": "",
          "m_warp": 0,
          "m_wait": 0,
          "m_speed_scale": 0,
          "m_activateEnemyNodeAbilityIds": [],
          "m_deactivateEnemyNodeAbilityIds": []
        },
        {
          "m_pos": {
            "x": 1119.2308,
            "y": 433.84613
          },
          "m_tag": "",
          "m_warp": 0,
          "m_wait": 0,
          "m_speed_scale": 0,
          "m_activateEnemyNodeAbilityIds": [],
          "m_deactivateEnemyNodeAbilityIds": []
        },
        {
          "m_pos": {
            "x": 822.15814,
            "y": 437.56415
          },
          "m_tag": "",
          "m_warp": 0,
          "m_wait": 0,
          "m_speed_scale": 0,
          "m_activateEnemyNodeAbilityIds": [],
          "m_deactivateEnemyNodeAbilityIds": []
        },
        {
          "m_pos": {
            "x": 863.8651,
            "y": 532.3527
          },
          "m_tag": "",
          "m_warp": 0,
          "m_wait": 0,
          "m_speed_scale": 0,
          "m_activateEnemyNodeAbilityIds": [],
          "m_deactivateEnemyNodeAbilityIds": []
        },
        {
          "m_pos": {
            "x": 981.9873,
            "y": 745.47015
          },
          "m_tag": "",
          "m_warp": 300,
          "m_wait": 0,
          "m_speed_scale": 0,
          "m_activateEnemyNodeAbilityIds": [],
          "m_deactivateEnemyNodeAbilityIds": []
        },
        {
          "m_pos": {
            "x": 601.5604,
            "y": 747.14734
          },
          "m_tag": "",
          "m_warp": 0,
          "m_wait": 0,
          "m_speed_scale": 0,
          "m_activateEnemyNodeAbilityIds": [],
          "m_deactivateEnemyNodeAbilityIds": []
        },
        {
          "m_pos": {
            "x": 541.1816,
            "y": 557.62463
          },
          "m_tag": "",
          "m_warp": 0,
          "m_wait": 0,
          "m_speed_scale": 0,
          "m_activateEnemyNodeAbilityIds": [],
          "m_deactivateEnemyNodeAbilityIds": []
        },
        {
          "m_pos": {
            "x": 500.92902,
            "y": 438.54398
          },
          "m_tag": "",
          "m_warp": 0,
          "m_wait": 0,
          "m_speed_scale": 0,
          "m_activateEnemyNodeAbilityIds": [],
          "m_deactivateEnemyNodeAbilityIds": []
        },
        {
          "m_pos": {
            "x": -74.34792,
            "y": 443.57553
          },
          "m_tag": "",
          "m_warp": 0,
          "m_wait": 0,
          "m_speed_scale": 0,
          "m_activateEnemyNodeAbilityIds": [],
          "m_deactivateEnemyNodeAbilityIds": []
        }
      ]
    },
    {
      "m_routeId": 13,
      "m_omenPos": {
        "x": 0.0,
        "y": 0.0
      },
      "m_points": [
        {
          "m_pos": {
            "x": 1305.3848,
            "y": 449.2308
          },
          "m_tag": "",
          "m_warp": 0,
          "m_wait": 0,
          "m_speed_scale": 0,
          "m_activateEnemyNodeAbilityIds": [],
          "m_deactivateEnemyNodeAbilityIds": []
        },
        {
          "m_pos": {
            "x": 1119.2308,
            "y": 449.2308
          },
          "m_tag": "",
          "m_warp": 0,
          "m_wait": 0,
          "m_speed_scale": 0,
          "m_activateEnemyNodeAbilityIds": [],
          "m_deactivateEnemyNodeAbilityIds": []
        },
        {
          "m_pos": {
            "x": 802.82355,
            "y": 450.2843
          },
          "m_tag": "",
          "m_warp": 0,
          "m_wait": 0,
          "m_speed_scale": 0,
          "m_activateEnemyNodeAbilityIds": [],
          "m_deactivateEnemyNodeAbilityIds": []
        },
        {
          "m_pos": {
            "x": 839.72186,
            "y": 535.82117
          },
          "m_tag": "",
          "m_warp": 0,
          "m_wait": 0,
          "m_speed_scale": 0,
          "m_activateEnemyNodeAbilityIds": [],
          "m_deactivateEnemyNodeAbilityIds": []
        },
        {
          "m_pos": {
            "x": 947.06213,
            "y": 745.47015
          },
          "m_tag": "",
          "m_warp": 300,
          "m_wait": 0,
          "m_speed_scale": 0,
          "m_activateEnemyNodeAbilityIds": [],
          "m_deactivateEnemyNodeAbilityIds": []
        },
        {
          "m_pos": {
            "x": 626.7184,
            "y": 745.47015
          },
          "m_tag": "",
          "m_warp": 0,
          "m_wait": 0,
          "m_speed_scale": 0,
          "m_activateEnemyNodeAbilityIds": [],
          "m_deactivateEnemyNodeAbilityIds": []
        },
        {
          "m_pos": {
            "x": 562.9851,
            "y": 547.56146
          },
          "m_tag": "",
          "m_warp": 0,
          "m_wait": 0,
          "m_speed_scale": 0,
          "m_activateEnemyNodeAbilityIds": [],
          "m_deactivateEnemyNodeAbilityIds": []
        },
        {
          "m_pos": {
            "x": 531.11847,
            "y": 453.6387
          },
          "m_tag": "",
          "m_warp": 0,
          "m_wait": 0,
          "m_speed_scale": 0,
          "m_activateEnemyNodeAbilityIds": [],
          "m_deactivateEnemyNodeAbilityIds": []
        },
        {
          "m_pos": {
            "x": -72.67079,
            "y": 462.0247
          },
          "m_tag": "",
          "m_warp": 0,
          "m_wait": 0,
          "m_speed_scale": 0,
          "m_activateEnemyNodeAbilityIds": [],
          "m_deactivateEnemyNodeAbilityIds": []
        }
      ]
    },
    {
      "m_routeId": 14,
      "m_omenPos": {
        "x": 0.0,
        "y": 0.0
      },
      "m_points": [
        {
          "m_pos": {
            "x": 819.80774,
            "y": -135.94022
          },
          "m_tag": "",
          "m_warp": 0,
          "m_wait": 99999,
          "m_speed_scale": 0,
          "m_activateEnemyNodeAbilityIds": [],
          "m_deactivateEnemyNodeAbilityIds": []
        },
        {
          "m_pos": {
            "x": 650.5769,
            "y": -114.78634
          },
          "m_tag": "",
          "m_warp": 0,
          "m_wait": 0,
          "m_speed_scale": 0,
          "m_activateEnemyNodeAbilityIds": [],
          "m_deactivateEnemyNodeAbilityIds": []
        }
      ]
    },
    {
      "m_routeId": 15,
      "m_omenPos": {
        "x": 0.0,
        "y": 0.0
      },
      "m_points": [
        {
          "m_pos": {
            "x": 1099.2307,
            "y": 287.69232
          },
          "m_tag": "",
          "m_warp": 0,
          "m_wait": 1500,
          "m_speed_scale": 0,
          "m_activateEnemyNodeAbilityIds": [],
          "m_deactivateEnemyNodeAbilityIds": []
        },
        {
          "m_pos": {
            "x": 953.0769,
            "y": 312.30768
          },
          "m_tag": "",
          "m_warp": 0,
          "m_wait": 0,
          "m_speed_scale": 0,
          "m_activateEnemyNodeAbilityIds": [],
          "m_deactivateEnemyNodeAbilityIds": []
        },
        {
          "m_pos": {
            "x": -54.551315,
            "y": 320.0427
          },
          "m_tag": "",
          "m_warp": 0,
          "m_wait": 0,
          "m_speed_scale": 0,
          "m_activateEnemyNodeAbilityIds": [],
          "m_deactivateEnemyNodeAbilityIds": []
        }
      ]
    },
    {
      "m_routeId": 16,
      "m_omenPos": {
        "x": 0.0,
        "y": 0.0
      },
      "m_points": [
        {
          "m_pos": {
            "x": 1331.5383,
            "y": 200.0
          },
          "m_tag": "",
          "m_warp": 0,
          "m_wait": 0,
          "m_speed_scale": 0,
          "m_activateEnemyNodeAbilityIds": [],
          "m_deactivateEnemyNodeAbilityIds": []
        },
        {
          "m_pos": {
            "x": 1234.6154,
            "y": 373.84616
          },
          "m_tag": "",
          "m_warp": 0,
          "m_wait": 0,
          "m_speed_scale": 0,
          "m_activateEnemyNodeAbilityIds": [],
          "m_deactivateEnemyNodeAbilityIds": []
        },
        {
          "m_pos": {
            "x": 1190.0,
            "y": 433.84613
          },
          "m_tag": "",
          "m_warp": 0,
          "m_wait": 0,
          "m_speed_scale": 0,
          "m_activateEnemyNodeAbilityIds": [],
          "m_deactivateEnemyNodeAbilityIds": []
        },
        {
          "m_pos": {
            "x": 1140.7693,
            "y": 486.15384
          },
          "m_tag": "",
          "m_warp": 0,
          "m_wait": 0,
          "m_speed_scale": 0,
          "m_activateEnemyNodeAbilityIds": [],
          "m_deactivateEnemyNodeAbilityIds": []
        },
        {
          "m_pos": {
            "x": 1083.8463,
            "y": 500.0
          },
          "m_tag": "",
          "m_warp": 0,
          "m_wait": 0,
          "m_speed_scale": 0,
          "m_activateEnemyNodeAbilityIds": [],
          "m_deactivateEnemyNodeAbilityIds": []
        },
        {
          "m_pos": {
            "x": 986.92303,
            "y": 493.8462
          },
          "m_tag": "",
          "m_warp": 0,
          "m_wait": 0,
          "m_speed_scale": 0,
          "m_activateEnemyNodeAbilityIds": [],
          "m_deactivateEnemyNodeAbilityIds": []
        },
        {
          "m_pos": {
            "x": 908.46155,
            "y": 481.53848
          },
          "m_tag": "",
          "m_warp": 0,
          "m_wait": 0,
          "m_speed_scale": 0,
          "m_activateEnemyNodeAbilityIds": [],
          "m_deactivateEnemyNodeAbilityIds": []
        },
        {
          "m_pos": {
            "x": 828.46155,
            "y": 444.61542
          },
          "m_tag": "",
          "m_warp": 0,
          "m_wait": 0,
          "m_speed_scale": 0,
          "m_activateEnemyNodeAbilityIds": [],
          "m_deactivateEnemyNodeAbilityIds": []
        },
        {
          "m_pos": {
            "x": 777.6924,
            "y": 406.15387
          },
          "m_tag": "",
          "m_warp": 0,
          "m_wait": 0,
          "m_speed_scale": 0,
          "m_activateEnemyNodeAbilityIds": [],
          "m_deactivateEnemyNodeAbilityIds": []
        },
        {
          "m_pos": {
            "x": 736.1539,
            "y": 369.23074
          },
          "m_tag": "",
          "m_warp": 0,
          "m_wait": 0,
          "m_speed_scale": 0,
          "m_activateEnemyNodeAbilityIds": [],
          "m_deactivateEnemyNodeAbilityIds": []
        },
        {
          "m_pos": {
            "x": 693.07697,
            "y": 330.76923
          },
          "m_tag": "",
          "m_warp": 0,
          "m_wait": 0,
          "m_speed_scale": 0,
          "m_activateEnemyNodeAbilityIds": [],
          "m_deactivateEnemyNodeAbilityIds": []
        },
        {
          "m_pos": {
            "x": 648.46155,
            "y": 278.46152
          },
          "m_tag": "",
          "m_warp": 0,
          "m_wait": 0,
          "m_speed_scale": 0,
          "m_activateEnemyNodeAbilityIds": [],
          "m_deactivateEnemyNodeAbilityIds": []
        },
        {
          "m_pos": {
            "x": 593.0769,
            "y": 244.61542
          },
          "m_tag": "",
          "m_warp": 0,
          "m_wait": 0,
          "m_speed_scale": 0,
          "m_activateEnemyNodeAbilityIds": [],
          "m_deactivateEnemyNodeAbilityIds": []
        },
        {
          "m_pos": {
            "x": 526.9231,
            "y": 218.46153
          },
          "m_tag": "",
          "m_warp": 0,
          "m_wait": 0,
          "m_speed_scale": 0,
          "m_activateEnemyNodeAbilityIds": [],
          "m_deactivateEnemyNodeAbilityIds": []
        },
        {
          "m_pos": {
            "x": 463.84616,
            "y": 243.07692
          },
          "m_tag": "",
          "m_warp": 0,
          "m_wait": 0,
          "m_speed_scale": 0,
          "m_activateEnemyNodeAbilityIds": [],
          "m_deactivateEnemyNodeAbilityIds": []
        },
        {
          "m_pos": {
            "x": 399.23077,
            "y": 307.69232
          },
          "m_tag": "",
          "m_warp": 0,
          "m_wait": 0,
          "m_speed_scale": 0,
          "m_activateEnemyNodeAbilityIds": [],
          "m_deactivateEnemyNodeAbilityIds": []
        },
        {
          "m_pos": {
            "x": 334.6154,
            "y": 358.46152
          },
          "m_tag": "",
          "m_warp": 0,
          "m_wait": 0,
          "m_speed_scale": 0,
          "m_activateEnemyNodeAbilityIds": [],
          "m_deactivateEnemyNodeAbilityIds": []
        },
        {
          "m_pos": {
            "x": 268.46155,
            "y": 427.69232
          },
          "m_tag": "",
          "m_warp": 0,
          "m_wait": 0,
          "m_speed_scale": 0,
          "m_activateEnemyNodeAbilityIds": [],
          "m_deactivateEnemyNodeAbilityIds": []
        },
        {
          "m_pos": {
            "x": 200.76918,
            "y": 475.3846
          },
          "m_tag": "",
          "m_warp": 0,
          "m_wait": 0,
          "m_speed_scale": 0,
          "m_activateEnemyNodeAbilityIds": [],
          "m_deactivateEnemyNodeAbilityIds": []
        },
        {
          "m_pos": {
            "x": 130.00002,
            "y": 495.38464
          },
          "m_tag": "",
          "m_warp": 0,
          "m_wait": 0,
          "m_speed_scale": 0,
          "m_activateEnemyNodeAbilityIds": [],
          "m_deactivateEnemyNodeAbilityIds": []
        },
        {
          "m_pos": {
            "x": 37.692307,
            "y": 478.46155
          },
          "m_tag": "",
          "m_warp": 0,
          "m_wait": 0,
          "m_speed_scale": 0,
          "m_activateEnemyNodeAbilityIds": [],
          "m_deactivateEnemyNodeAbilityIds": []
        },
        {
          "m_pos": {
            "x": -37.692356,
            "y": 440.0
          },
          "m_tag": "",
          "m_warp": 0,
          "m_wait": 0,
          "m_speed_scale": 0,
          "m_activateEnemyNodeAbilityIds": [],
          "m_deactivateEnemyNodeAbilityIds": []
        }
      ]
    },
    {
      "m_routeId": 17,
      "m_omenPos": {
        "x": 0.0,
        "y": 0.0
      },
      "m_points": [
        {
          "m_pos": {
            "x": 1326.923,
            "y": 169.23076
          },
          "m_tag": "",
          "m_warp": 0,
          "m_wait": 0,
          "m_speed_scale": 0,
          "m_activateEnemyNodeAbilityIds": [],
          "m_deactivateEnemyNodeAbilityIds": []
        },
        {
          "m_pos": {
            "x": 1229.9999,
            "y": 343.0769
          },
          "m_tag": "",
          "m_warp": 0,
          "m_wait": 0,
          "m_speed_scale": 0,
          "m_activateEnemyNodeAbilityIds": [],
          "m_deactivateEnemyNodeAbilityIds": []
        },
        {
          "m_pos": {
            "x": 1185.3845,
            "y": 403.07687
          },
          "m_tag": "",
          "m_warp": 0,
          "m_wait": 0,
          "m_speed_scale": 0,
          "m_activateEnemyNodeAbilityIds": [],
          "m_deactivateEnemyNodeAbilityIds": []
        },
        {
          "m_pos": {
            "x": 1136.1539,
            "y": 455.38458
          },
          "m_tag": "",
          "m_warp": 0,
          "m_wait": 0,
          "m_speed_scale": 0,
          "m_activateEnemyNodeAbilityIds": [],
          "m_deactivateEnemyNodeAbilityIds": []
        },
        {
          "m_pos": {
            "x": 1079.2308,
            "y": 469.23074
          },
          "m_tag": "",
          "m_warp": 0,
          "m_wait": 0,
          "m_speed_scale": 0,
          "m_activateEnemyNodeAbilityIds": [],
          "m_deactivateEnemyNodeAbilityIds": []
        },
        {
          "m_pos": {
            "x": 982.30774,
            "y": 463.07693
          },
          "m_tag": "",
          "m_warp": 0,
          "m_wait": 0,
          "m_speed_scale": 0,
          "m_activateEnemyNodeAbilityIds": [],
          "m_deactivateEnemyNodeAbilityIds": []
        },
        {
          "m_pos": {
            "x": 903.84625,
            "y": 450.76923
          },
          "m_tag": "",
          "m_warp": 0,
          "m_wait": 0,
          "m_speed_scale": 0,
          "m_activateEnemyNodeAbilityIds": [],
          "m_deactivateEnemyNodeAbilityIds": []
        },
        {
          "m_pos": {
            "x": 823.84625,
            "y": 413.84616
          },
          "m_tag": "",
          "m_warp": 0,
          "m_wait": 0,
          "m_speed_scale": 0,
          "m_activateEnemyNodeAbilityIds": [],
          "m_deactivateEnemyNodeAbilityIds": []
        },
        {
          "m_pos": {
            "x": 773.077,
            "y": 375.3846
          },
          "m_tag": "",
          "m_warp": 0,
          "m_wait": 0,
          "m_speed_scale": 0,
          "m_activateEnemyNodeAbilityIds": [],
          "m_deactivateEnemyNodeAbilityIds": []
        },
        {
          "m_pos": {
            "x": 731.5386,
            "y": 338.4615
          },
          "m_tag": "",
          "m_warp": 0,
          "m_wait": 0,
          "m_speed_scale": 0,
          "m_activateEnemyNodeAbilityIds": [],
          "m_deactivateEnemyNodeAbilityIds": []
        },
        {
          "m_pos": {
            "x": 688.4616,
            "y": 299.99997
          },
          "m_tag": "",
          "m_warp": 0,
          "m_wait": 0,
          "m_speed_scale": 0,
          "m_activateEnemyNodeAbilityIds": [],
          "m_deactivateEnemyNodeAbilityIds": []
        },
        {
          "m_pos": {
            "x": 643.84625,
            "y": 247.69225
          },
          "m_tag": "",
          "m_warp": 0,
          "m_wait": 0,
          "m_speed_scale": 0,
          "m_activateEnemyNodeAbilityIds": [],
          "m_deactivateEnemyNodeAbilityIds": []
        },
        {
          "m_pos": {
            "x": 588.4616,
            "y": 213.84616
          },
          "m_tag": "",
          "m_warp": 0,
          "m_wait": 0,
          "m_speed_scale": 0,
          "m_activateEnemyNodeAbilityIds": [],
          "m_deactivateEnemyNodeAbilityIds": []
        },
        {
          "m_pos": {
            "x": 522.3078,
            "y": 187.69229
          },
          "m_tag": "",
          "m_warp": 0,
          "m_wait": 0,
          "m_speed_scale": 0,
          "m_activateEnemyNodeAbilityIds": [],
          "m_deactivateEnemyNodeAbilityIds": []
        },
        {
          "m_pos": {
            "x": 459.2308,
            "y": 212.3077
          },
          "m_tag": "",
          "m_warp": 0,
          "m_wait": 0,
          "m_speed_scale": 0,
          "m_activateEnemyNodeAbilityIds": [],
          "m_deactivateEnemyNodeAbilityIds": []
        },
        {
          "m_pos": {
            "x": 394.61545,
            "y": 276.92307
          },
          "m_tag": "",
          "m_warp": 0,
          "m_wait": 0,
          "m_speed_scale": 0,
          "m_activateEnemyNodeAbilityIds": [],
          "m_deactivateEnemyNodeAbilityIds": []
        },
        {
          "m_pos": {
            "x": 330.00006,
            "y": 327.69226
          },
          "m_tag": "",
          "m_warp": 0,
          "m_wait": 0,
          "m_speed_scale": 0,
          "m_activateEnemyNodeAbilityIds": [],
          "m_deactivateEnemyNodeAbilityIds": []
        },
        {
          "m_pos": {
            "x": 263.8462,
            "y": 396.92307
          },
          "m_tag": "",
          "m_warp": 0,
          "m_wait": 0,
          "m_speed_scale": 0,
          "m_activateEnemyNodeAbilityIds": [],
          "m_deactivateEnemyNodeAbilityIds": []
        },
        {
          "m_pos": {
            "x": 196.15388,
            "y": 444.61536
          },
          "m_tag": "",
          "m_warp": 0,
          "m_wait": 0,
          "m_speed_scale": 0,
          "m_activateEnemyNodeAbilityIds": [],
          "m_deactivateEnemyNodeAbilityIds": []
        },
        {
          "m_pos": {
            "x": 125.38467,
            "y": 464.6154
          },
          "m_tag": "",
          "m_warp": 0,
          "m_wait": 0,
          "m_speed_scale": 0,
          "m_activateEnemyNodeAbilityIds": [],
          "m_deactivateEnemyNodeAbilityIds": []
        },
        {
          "m_pos": {
            "x": 33.077003,
            "y": 447.6923
          },
          "m_tag": "",
          "m_warp": 0,
          "m_wait": 0,
          "m_speed_scale": 0,
          "m_activateEnemyNodeAbilityIds": [],
          "m_deactivateEnemyNodeAbilityIds": []
        },
        {
          "m_pos": {
            "x": -42.30771,
            "y": 409.23074
          },
          "m_tag": "",
          "m_warp": 0,
          "m_wait": 0,
          "m_speed_scale": 0,
          "m_activateEnemyNodeAbilityIds": [],
          "m_deactivateEnemyNodeAbilityIds": []
        }
      ]
    },
    {
      "m_routeId": 18,
      "m_omenPos": {
        "x": 0.0,
        "y": 0.0
      },
      "m_points": [
        {
          "m_pos": {
            "x": 1325.3845,
            "y": 141.53857
          },
          "m_tag": "",
          "m_warp": 0,
          "m_wait": 0,
          "m_speed_scale": 0,
          "m_activateEnemyNodeAbilityIds": [],
          "m_deactivateEnemyNodeAbilityIds": []
        },
        {
          "m_pos": {
            "x": 1228.4614,
            "y": 315.38464
          },
          "m_tag": "",
          "m_warp": 0,
          "m_wait": 0,
          "m_speed_scale": 0,
          "m_activateEnemyNodeAbilityIds": [],
          "m_deactivateEnemyNodeAbilityIds": []
        },
        {
          "m_pos": {
            "x": 1183.8461,
            "y": 375.38464
          },
          "m_tag": "",
          "m_warp": 0,
          "m_wait": 0,
          "m_speed_scale": 0,
          "m_activateEnemyNodeAbilityIds": [],
          "m_deactivateEnemyNodeAbilityIds": []
        },
        {
          "m_pos": {
            "x": 1134.6154,
            "y": 427.69232
          },
          "m_tag": "",
          "m_warp": 0,
          "m_wait": 0,
          "m_speed_scale": 0,
          "m_activateEnemyNodeAbilityIds": [],
          "m_deactivateEnemyNodeAbilityIds": []
        },
        {
          "m_pos": {
            "x": 1077.6924,
            "y": 441.53848
          },
          "m_tag": "",
          "m_warp": 0,
          "m_wait": 0,
          "m_speed_scale": 0,
          "m_activateEnemyNodeAbilityIds": [],
          "m_deactivateEnemyNodeAbilityIds": []
        },
        {
          "m_pos": {
            "x": 980.76917,
            "y": 435.38464
          },
          "m_tag": "",
          "m_warp": 0,
          "m_wait": 0,
          "m_speed_scale": 0,
          "m_activateEnemyNodeAbilityIds": [],
          "m_deactivateEnemyNodeAbilityIds": []
        },
        {
          "m_pos": {
            "x": 902.3077,
            "y": 423.07697
          },
          "m_tag": "",
          "m_warp": 0,
          "m_wait": 0,
          "m_speed_scale": 0,
          "m_activateEnemyNodeAbilityIds": [],
          "m_deactivateEnemyNodeAbilityIds": []
        },
        {
          "m_pos": {
            "x": 822.3078,
            "y": 386.1539
          },
          "m_tag": "",
          "m_warp": 0,
          "m_wait": 0,
          "m_speed_scale": 0,
          "m_activateEnemyNodeAbilityIds": [],
          "m_deactivateEnemyNodeAbilityIds": []
        },
        {
          "m_pos": {
            "x": 771.5385,
            "y": 347.69238
          },
          "m_tag": "",
          "m_warp": 0,
          "m_wait": 0,
          "m_speed_scale": 0,
          "m_activateEnemyNodeAbilityIds": [],
          "m_deactivateEnemyNodeAbilityIds": []
        },
        {
          "m_pos": {
            "x": 730.00006,
            "y": 310.76926
          },
          "m_tag": "",
          "m_warp": 0,
          "m_wait": 0,
          "m_speed_scale": 0,
          "m_activateEnemyNodeAbilityIds": [],
          "m_deactivateEnemyNodeAbilityIds": []
        },
        {
          "m_pos": {
            "x": 686.9231,
            "y": 272.30774
          },
          "m_tag": "",
          "m_warp": 0,
          "m_wait": 0,
          "m_speed_scale": 0,
          "m_activateEnemyNodeAbilityIds": [],
          "m_deactivateEnemyNodeAbilityIds": []
        },
        {
          "m_pos": {
            "x": 642.30774,
            "y": 220.0
          },
          "m_tag": "",
          "m_warp": 0,
          "m_wait": 0,
          "m_speed_scale": 0,
          "m_activateEnemyNodeAbilityIds": [],
          "m_deactivateEnemyNodeAbilityIds": []
        },
        {
          "m_pos": {
            "x": 586.9231,
            "y": 186.15392
          },
          "m_tag": "",
          "m_warp": 0,
          "m_wait": 0,
          "m_speed_scale": 0,
          "m_activateEnemyNodeAbilityIds": [],
          "m_deactivateEnemyNodeAbilityIds": []
        },
        {
          "m_pos": {
            "x": 520.7693,
            "y": 160.00006
          },
          "m_tag": "",
          "m_warp": 0,
          "m_wait": 0,
          "m_speed_scale": 0,
          "m_activateEnemyNodeAbilityIds": [],
          "m_deactivateEnemyNodeAbilityIds": []
        },
        {
          "m_pos": {
            "x": 457.6923,
            "y": 184.61545
          },
          "m_tag": "",
          "m_warp": 0,
          "m_wait": 0,
          "m_speed_scale": 0,
          "m_activateEnemyNodeAbilityIds": [],
          "m_deactivateEnemyNodeAbilityIds": []
        },
        {
          "m_pos": {
            "x": 393.07693,
            "y": 249.23082
          },
          "m_tag": "",
          "m_warp": 0,
          "m_wait": 0,
          "m_speed_scale": 0,
          "m_activateEnemyNodeAbilityIds": [],
          "m_deactivateEnemyNodeAbilityIds": []
        },
        {
          "m_pos": {
            "x": 328.46155,
            "y": 300.00003
          },
          "m_tag": "",
          "m_warp": 0,
          "m_wait": 0,
          "m_speed_scale": 0,
          "m_activateEnemyNodeAbilityIds": [],
          "m_deactivateEnemyNodeAbilityIds": []
        },
        {
          "m_pos": {
            "x": 262.30768,
            "y": 369.2308
          },
          "m_tag": "",
          "m_warp": 0,
          "m_wait": 0,
          "m_speed_scale": 0,
          "m_activateEnemyNodeAbilityIds": [],
          "m_deactivateEnemyNodeAbilityIds": []
        },
        {
          "m_pos": {
            "x": 194.61536,
            "y": 416.9231
          },
          "m_tag": "",
          "m_warp": 0,
          "m_wait": 0,
          "m_speed_scale": 0,
          "m_activateEnemyNodeAbilityIds": [],
          "m_deactivateEnemyNodeAbilityIds": []
        },
        {
          "m_pos": {
            "x": 123.846146,
            "y": 436.92313
          },
          "m_tag": "",
          "m_warp": 0,
          "m_wait": 0,
          "m_speed_scale": 0,
          "m_activateEnemyNodeAbilityIds": [],
          "m_deactivateEnemyNodeAbilityIds": []
        },
        {
          "m_pos": {
            "x": 31.538486,
            "y": 420.00003
          },
          "m_tag": "",
          "m_warp": 0,
          "m_wait": 0,
          "m_speed_scale": 0,
          "m_activateEnemyNodeAbilityIds": [],
          "m_deactivateEnemyNodeAbilityIds": []
        },
        {
          "m_pos": {
            "x": -43.846226,
            "y": 381.5385
          },
          "m_tag": "",
          "m_warp": 0,
          "m_wait": 0,
          "m_speed_scale": 0,
          "m_activateEnemyNodeAbilityIds": [],
          "m_deactivateEnemyNodeAbilityIds": []
        }
      ]
    },
    {
      "m_routeId": 19,
      "m_omenPos": {
        "x": 0.0,
        "y": 0.0
      },
      "m_points": [
        {
          "m_pos": {
            "x": 1316.1539,
            "y": 467.69232
          },
          "m_tag": "",
          "m_warp": 0,
          "m_wait": 0,
          "m_speed_scale": 0,
          "m_activateEnemyNodeAbilityIds": [],
          "m_deactivateEnemyNodeAbilityIds": []
        },
        {
          "m_pos": {
            "x": 1193.0769,
            "y": 498.46155
          },
          "m_tag": "",
          "m_warp": 0,
          "m_wait": 0,
          "m_speed_scale": 0,
          "m_activateEnemyNodeAbilityIds": [],
          "m_deactivateEnemyNodeAbilityIds": []
        },
        {
          "m_pos": {
            "x": 1068.4617,
            "y": 509.2308
          },
          "m_tag": "",
          "m_warp": 0,
          "m_wait": 0,
          "m_speed_scale": 0,
          "m_activateEnemyNodeAbilityIds": [],
          "m_deactivateEnemyNodeAbilityIds": []
        },
        {
          "m_pos": {
            "x": 893.0769,
            "y": 513.8461
          },
          "m_tag": "",
          "m_warp": 0,
          "m_wait": 0,
          "m_speed_scale": 0,
          "m_activateEnemyNodeAbilityIds": [],
          "m_deactivateEnemyNodeAbilityIds": []
        },
        {
          "m_pos": {
            "x": 774.6154,
            "y": 513.8461
          },
          "m_tag": "",
          "m_warp": 0,
          "m_wait": 0,
          "m_speed_scale": 0,
          "m_activateEnemyNodeAbilityIds": [],
          "m_deactivateEnemyNodeAbilityIds": []
        },
        {
          "m_pos": {
            "x": 633.0769,
            "y": 513.8461
          },
          "m_tag": "",
          "m_warp": 0,
          "m_wait": 0,
          "m_speed_scale": 0,
          "m_activateEnemyNodeAbilityIds": [],
          "m_deactivateEnemyNodeAbilityIds": []
        },
        {
          "m_pos": {
            "x": 476.15384,
            "y": 513.8461
          },
          "m_tag": "",
          "m_warp": 0,
          "m_wait": 0,
          "m_speed_scale": 0,
          "m_activateEnemyNodeAbilityIds": [],
          "m_deactivateEnemyNodeAbilityIds": []
        },
        {
          "m_pos": {
            "x": 308.46155,
            "y": 512.3077
          },
          "m_tag": "",
          "m_warp": 0,
          "m_wait": 0,
          "m_speed_scale": 0,
          "m_activateEnemyNodeAbilityIds": [],
          "m_deactivateEnemyNodeAbilityIds": []
        },
        {
          "m_pos": {
            "x": 179.23074,
            "y": 496.92307
          },
          "m_tag": "",
          "m_warp": 0,
          "m_wait": 0,
          "m_speed_scale": 0,
          "m_activateEnemyNodeAbilityIds": [],
          "m_deactivateEnemyNodeAbilityIds": []
        },
        {
          "m_pos": {
            "x": 99.23072,
            "y": 480.00003
          },
          "m_tag": "",
          "m_warp": 0,
          "m_wait": 0,
          "m_speed_scale": 0,
          "m_activateEnemyNodeAbilityIds": [],
          "m_deactivateEnemyNodeAbilityIds": []
        },
        {
          "m_pos": {
            "x": -45.384693,
            "y": 432.30768
          },
          "m_tag": "",
          "m_warp": 0,
          "m_wait": 0,
          "m_speed_scale": 0,
          "m_activateEnemyNodeAbilityIds": [],
          "m_deactivateEnemyNodeAbilityIds": []
        }
      ]
    },
    {
      "m_routeId": 20,
      "m_omenPos": {
        "x": 0.0,
        "y": 0.0
      },
      "m_points": [
        {
          "m_pos": {
            "x": 1317.6924,
            "y": 484.61548
          },
          "m_tag": "",
          "m_warp": 0,
          "m_wait": 0,
          "m_speed_scale": 0,
          "m_activateEnemyNodeAbilityIds": [],
          "m_deactivateEnemyNodeAbilityIds": []
        },
        {
          "m_pos": {
            "x": 1194.6154,
            "y": 515.38464
          },
          "m_tag": "",
          "m_warp": 0,
          "m_wait": 0,
          "m_speed_scale": 0,
          "m_activateEnemyNodeAbilityIds": [],
          "m_deactivateEnemyNodeAbilityIds": []
        },
        {
          "m_pos": {
            "x": 1070.0002,
            "y": 526.15393
          },
          "m_tag": "",
          "m_warp": 0,
          "m_wait": 0,
          "m_speed_scale": 0,
          "m_activateEnemyNodeAbilityIds": [],
          "m_deactivateEnemyNodeAbilityIds": []
        },
        {
          "m_pos": {
            "x": 894.61536,
            "y": 530.7692
          },
          "m_tag": "",
          "m_warp": 0,
          "m_wait": 0,
          "m_speed_scale": 0,
          "m_activateEnemyNodeAbilityIds": [],
          "m_deactivateEnemyNodeAbilityIds": []
        },
        {
          "m_pos": {
            "x": 776.15393,
            "y": 530.7692
          },
          "m_tag": "",
          "m_warp": 0,
          "m_wait": 0,
          "m_speed_scale": 0,
          "m_activateEnemyNodeAbilityIds": [],
          "m_deactivateEnemyNodeAbilityIds": []
        },
        {
          "m_pos": {
            "x": 634.6154,
            "y": 530.7692
          },
          "m_tag": "",
          "m_warp": 0,
          "m_wait": 0,
          "m_speed_scale": 0,
          "m_activateEnemyNodeAbilityIds": [],
          "m_deactivateEnemyNodeAbilityIds": []
        },
        {
          "m_pos": {
            "x": 477.69235,
            "y": 530.7692
          },
          "m_tag": "",
          "m_warp": 0,
          "m_wait": 0,
          "m_speed_scale": 0,
          "m_activateEnemyNodeAbilityIds": [],
          "m_deactivateEnemyNodeAbilityIds": []
        },
        {
          "m_pos": {
            "x": 310.00006,
            "y": 529.23083
          },
          "m_tag": "",
          "m_warp": 0,
          "m_wait": 0,
          "m_speed_scale": 0,
          "m_activateEnemyNodeAbilityIds": [],
          "m_deactivateEnemyNodeAbilityIds": []
        },
        {
          "m_pos": {
            "x": 180.76926,
            "y": 513.8462
          },
          "m_tag": "",
          "m_warp": 0,
          "m_wait": 0,
          "m_speed_scale": 0,
          "m_activateEnemyNodeAbilityIds": [],
          "m_deactivateEnemyNodeAbilityIds": []
        },
        {
          "m_pos": {
            "x": 100.76923,
            "y": 496.92316
          },
          "m_tag": "",
          "m_warp": 0,
          "m_wait": 0,
          "m_speed_scale": 0,
          "m_activateEnemyNodeAbilityIds": [],
          "m_deactivateEnemyNodeAbilityIds": []
        },
        {
          "m_pos": {
            "x": -43.846176,
            "y": 449.2308
          },
          "m_tag": "",
          "m_warp": 0,
          "m_wait": 0,
          "m_speed_scale": 0,
          "m_activateEnemyNodeAbilityIds": [],
          "m_deactivateEnemyNodeAbilityIds": []
        }
      ]
    },
    {
      "m_routeId": 21,
      "m_omenPos": {
        "x": 0.0,
        "y": 0.0
      },
      "m_points": [
        {
          "m_pos": {
            "x": 1316.1539,
            "y": 504.6155
          },
          "m_tag": "",
          "m_warp": 0,
          "m_wait": 0,
          "m_speed_scale": 0,
          "m_activateEnemyNodeAbilityIds": [],
          "m_deactivateEnemyNodeAbilityIds": []
        },
        {
          "m_pos": {
            "x": 1193.0769,
            "y": 535.38464
          },
          "m_tag": "",
          "m_warp": 0,
          "m_wait": 0,
          "m_speed_scale": 0,
          "m_activateEnemyNodeAbilityIds": [],
          "m_deactivateEnemyNodeAbilityIds": []
        },
        {
          "m_pos": {
            "x": 1068.4618,
            "y": 546.154
          },
          "m_tag": "",
          "m_warp": 0,
          "m_wait": 0,
          "m_speed_scale": 0,
          "m_activateEnemyNodeAbilityIds": [],
          "m_deactivateEnemyNodeAbilityIds": []
        },
        {
          "m_pos": {
            "x": 893.0769,
            "y": 550.7692
          },
          "m_tag": "",
          "m_warp": 0,
          "m_wait": 0,
          "m_speed_scale": 0,
          "m_activateEnemyNodeAbilityIds": [],
          "m_deactivateEnemyNodeAbilityIds": []
        },
        {
          "m_pos": {
            "x": 774.6155,
            "y": 550.7692
          },
          "m_tag": "",
          "m_warp": 0,
          "m_wait": 0,
          "m_speed_scale": 0,
          "m_activateEnemyNodeAbilityIds": [],
          "m_deactivateEnemyNodeAbilityIds": []
        },
        {
          "m_pos": {
            "x": 633.07697,
            "y": 550.7692
          },
          "m_tag": "",
          "m_warp": 0,
          "m_wait": 0,
          "m_speed_scale": 0,
          "m_activateEnemyNodeAbilityIds": [],
          "m_deactivateEnemyNodeAbilityIds": []
        },
        {
          "m_pos": {
            "x": 476.15384,
            "y": 550.7692
          },
          "m_tag": "",
          "m_warp": 0,
          "m_wait": 0,
          "m_speed_scale": 0,
          "m_activateEnemyNodeAbilityIds": [],
          "m_deactivateEnemyNodeAbilityIds": []
        },
        {
          "m_pos": {
            "x": 308.46158,
            "y": 549.23083
          },
          "m_tag": "",
          "m_warp": 0,
          "m_wait": 0,
          "m_speed_scale": 0,
          "m_activateEnemyNodeAbilityIds": [],
          "m_deactivateEnemyNodeAbilityIds": []
        },
        {
          "m_pos": {
            "x": 179.23079,
            "y": 533.84625
          },
          "m_tag": "",
          "m_warp": 0,
          "m_wait": 0,
          "m_speed_scale": 0,
          "m_activateEnemyNodeAbilityIds": [],
          "m_deactivateEnemyNodeAbilityIds": []
        },
        {
          "m_pos": {
            "x": 99.23077,
            "y": 516.9232
          },
          "m_tag": "",
          "m_warp": 0,
          "m_wait": 0,
          "m_speed_scale": 0,
          "m_activateEnemyNodeAbilityIds": [],
          "m_deactivateEnemyNodeAbilityIds": []
        },
        {
          "m_pos": {
            "x": -45.384644,
            "y": 469.23083
          },
          "m_tag": "",
          "m_warp": 0,
          "m_wait": 0,
          "m_speed_scale": 0,
          "m_activateEnemyNodeAbilityIds": [],
          "m_deactivateEnemyNodeAbilityIds": []
        }
      ]
    },
    {
      "m_routeId": 22,
      "m_omenPos": {
        "x": 0.0,
        "y": 0.0
      },
      "m_points": [
        {
          "m_pos": {
            "x": 1317.6924,
            "y": 484.61548
          },
          "m_tag": "",
          "m_warp": 0,
          "m_wait": 0,
          "m_speed_scale": 0,
          "m_activateEnemyNodeAbilityIds": [],
          "m_deactivateEnemyNodeAbilityIds": []
        },
        {
          "m_pos": {
            "x": 1191.5385,
            "y": 513.8461
          },
          "m_tag": "",
          "m_warp": 0,
          "m_wait": 0,
          "m_speed_scale": 0,
          "m_activateEnemyNodeAbilityIds": [],
          "m_deactivateEnemyNodeAbilityIds": []
        },
        {
          "m_pos": {
            "x": 1090.0,
            "y": 527.6923
          },
          "m_tag": "",
          "m_warp": 0,
          "m_wait": 700,
          "m_speed_scale": 0,
          "m_activateEnemyNodeAbilityIds": [],
          "m_deactivateEnemyNodeAbilityIds": []
        },
        {
          "m_pos": {
            "x": 894.61536,
            "y": 530.7692
          },
          "m_tag": "",
          "m_warp": 0,
          "m_wait": 0,
          "m_speed_scale": 0,
          "m_activateEnemyNodeAbilityIds": [],
          "m_deactivateEnemyNodeAbilityIds": []
        },
        {
          "m_pos": {
            "x": 776.15393,
            "y": 530.7692
          },
          "m_tag": "",
          "m_warp": 0,
          "m_wait": 0,
          "m_speed_scale": 0,
          "m_activateEnemyNodeAbilityIds": [],
          "m_deactivateEnemyNodeAbilityIds": []
        },
        {
          "m_pos": {
            "x": 634.6154,
            "y": 530.7692
          },
          "m_tag": "",
          "m_warp": 0,
          "m_wait": 0,
          "m_speed_scale": 0,
          "m_activateEnemyNodeAbilityIds": [],
          "m_deactivateEnemyNodeAbilityIds": []
        },
        {
          "m_pos": {
            "x": 477.69235,
            "y": 530.7692
          },
          "m_tag": "",
          "m_warp": 0,
          "m_wait": 0,
          "m_speed_scale": 0,
          "m_activateEnemyNodeAbilityIds": [],
          "m_deactivateEnemyNodeAbilityIds": []
        },
        {
          "m_pos": {
            "x": 310.00006,
            "y": 529.23083
          },
          "m_tag": "",
          "m_warp": 0,
          "m_wait": 0,
          "m_speed_scale": 0,
          "m_activateEnemyNodeAbilityIds": [],
          "m_deactivateEnemyNodeAbilityIds": []
        },
        {
          "m_pos": {
            "x": 180.76926,
            "y": 513.8462
          },
          "m_tag": "",
          "m_warp": 0,
          "m_wait": 0,
          "m_speed_scale": 0,
          "m_activateEnemyNodeAbilityIds": [],
          "m_deactivateEnemyNodeAbilityIds": []
        },
        {
          "m_pos": {
            "x": 100.76923,
            "y": 496.92316
          },
          "m_tag": "",
          "m_warp": 0,
          "m_wait": 0,
          "m_speed_scale": 0,
          "m_activateEnemyNodeAbilityIds": [],
          "m_deactivateEnemyNodeAbilityIds": []
        },
        {
          "m_pos": {
            "x": -43.846176,
            "y": 449.2308
          },
          "m_tag": "",
          "m_warp": 0,
          "m_wait": 0,
          "m_speed_scale": 0,
          "m_activateEnemyNodeAbilityIds": [],
          "m_deactivateEnemyNodeAbilityIds": []
        }
      ]
    },
    {
      "m_routeId": 23,
      "m_omenPos": {
        "x": 0.0,
        "y": 0.0
      },
      "m_points": [
        {
          "m_pos": {
            "x": 1316.1539,
            "y": 467.69232
          },
          "m_tag": "",
          "m_warp": 0,
          "m_wait": 0,
          "m_speed_scale": 0,
          "m_activateEnemyNodeAbilityIds": [],
          "m_deactivateEnemyNodeAbilityIds": []
        },
        {
          "m_pos": {
            "x": 1222.3077,
            "y": 489.23077
          },
          "m_tag": "",
          "m_warp": 0,
          "m_wait": 800,
          "m_speed_scale": 0,
          "m_activateEnemyNodeAbilityIds": [],
          "m_deactivateEnemyNodeAbilityIds": []
        },
        {
          "m_pos": {
            "x": 1068.4617,
            "y": 509.2308
          },
          "m_tag": "",
          "m_warp": 0,
          "m_wait": 0,
          "m_speed_scale": 0,
          "m_activateEnemyNodeAbilityIds": [],
          "m_deactivateEnemyNodeAbilityIds": []
        },
        {
          "m_pos": {
            "x": 893.0769,
            "y": 513.8461
          },
          "m_tag": "",
          "m_warp": 0,
          "m_wait": 0,
          "m_speed_scale": 0,
          "m_activateEnemyNodeAbilityIds": [],
          "m_deactivateEnemyNodeAbilityIds": []
        },
        {
          "m_pos": {
            "x": 774.6154,
            "y": 513.8461
          },
          "m_tag": "",
          "m_warp": 0,
          "m_wait": 0,
          "m_speed_scale": 0,
          "m_activateEnemyNodeAbilityIds": [],
          "m_deactivateEnemyNodeAbilityIds": []
        },
        {
          "m_pos": {
            "x": 633.0769,
            "y": 513.8461
          },
          "m_tag": "",
          "m_warp": 0,
          "m_wait": 0,
          "m_speed_scale": 0,
          "m_activateEnemyNodeAbilityIds": [],
          "m_deactivateEnemyNodeAbilityIds": []
        },
        {
          "m_pos": {
            "x": 476.15384,
            "y": 513.8461
          },
          "m_tag": "",
          "m_warp": 0,
          "m_wait": 0,
          "m_speed_scale": 0,
          "m_activateEnemyNodeAbilityIds": [],
          "m_deactivateEnemyNodeAbilityIds": []
        },
        {
          "m_pos": {
            "x": 308.46155,
            "y": 512.3077
          },
          "m_tag": "",
          "m_warp": 0,
          "m_wait": 0,
          "m_speed_scale": 0,
          "m_activateEnemyNodeAbilityIds": [],
          "m_deactivateEnemyNodeAbilityIds": []
        },
        {
          "m_pos": {
            "x": 179.23074,
            "y": 496.92307
          },
          "m_tag": "",
          "m_warp": 0,
          "m_wait": 0,
          "m_speed_scale": 0,
          "m_activateEnemyNodeAbilityIds": [],
          "m_deactivateEnemyNodeAbilityIds": []
        },
        {
          "m_pos": {
            "x": 99.23072,
            "y": 480.00003
          },
          "m_tag": "",
          "m_warp": 0,
          "m_wait": 0,
          "m_speed_scale": 0,
          "m_activateEnemyNodeAbilityIds": [],
          "m_deactivateEnemyNodeAbilityIds": []
        },
        {
          "m_pos": {
            "x": -45.384693,
            "y": 432.30768
          },
          "m_tag": "",
          "m_warp": 0,
          "m_wait": 0,
          "m_speed_scale": 0,
          "m_activateEnemyNodeAbilityIds": [],
          "m_deactivateEnemyNodeAbilityIds": []
        }
      ]
    },
    {
      "m_routeId": 24,
      "m_omenPos": {
        "x": 0.0,
        "y": 0.0
      },
      "m_points": [
        {
          "m_pos": {
            "x": 1316.1539,
            "y": 504.6155
          },
          "m_tag": "",
          "m_warp": 0,
          "m_wait": 0,
          "m_speed_scale": 0,
          "m_activateEnemyNodeAbilityIds": [],
          "m_deactivateEnemyNodeAbilityIds": []
        },
        {
          "m_pos": {
            "x": 1159.2308,
            "y": 543.07697
          },
          "m_tag": "",
          "m_warp": 0,
          "m_wait": 750,
          "m_speed_scale": 0,
          "m_activateEnemyNodeAbilityIds": [],
          "m_deactivateEnemyNodeAbilityIds": []
        },
        {
          "m_pos": {
            "x": 1042.3077,
            "y": 550.7692
          },
          "m_tag": "",
          "m_warp": 0,
          "m_wait": 0,
          "m_speed_scale": 0,
          "m_activateEnemyNodeAbilityIds": [],
          "m_deactivateEnemyNodeAbilityIds": []
        },
        {
          "m_pos": {
            "x": 893.0769,
            "y": 550.7692
          },
          "m_tag": "",
          "m_warp": 0,
          "m_wait": 0,
          "m_speed_scale": 0,
          "m_activateEnemyNodeAbilityIds": [],
          "m_deactivateEnemyNodeAbilityIds": []
        },
        {
          "m_pos": {
            "x": 774.6155,
            "y": 550.7692
          },
          "m_tag": "",
          "m_warp": 0,
          "m_wait": 0,
          "m_speed_scale": 0,
          "m_activateEnemyNodeAbilityIds": [],
          "m_deactivateEnemyNodeAbilityIds": []
        },
        {
          "m_pos": {
            "x": 633.07697,
            "y": 550.7692
          },
          "m_tag": "",
          "m_warp": 0,
          "m_wait": 0,
          "m_speed_scale": 0,
          "m_activateEnemyNodeAbilityIds": [],
          "m_deactivateEnemyNodeAbilityIds": []
        },
        {
          "m_pos": {
            "x": 476.15384,
            "y": 550.7692
          },
          "m_tag": "",
          "m_warp": 0,
          "m_wait": 0,
          "m_speed_scale": 0,
          "m_activateEnemyNodeAbilityIds": [],
          "m_deactivateEnemyNodeAbilityIds": []
        },
        {
          "m_pos": {
            "x": 308.46158,
            "y": 549.23083
          },
          "m_tag": "",
          "m_warp": 0,
          "m_wait": 0,
          "m_speed_scale": 0,
          "m_activateEnemyNodeAbilityIds": [],
          "m_deactivateEnemyNodeAbilityIds": []
        },
        {
          "m_pos": {
            "x": 179.23079,
            "y": 533.84625
          },
          "m_tag": "",
          "m_warp": 0,
          "m_wait": 0,
          "m_speed_scale": 0,
          "m_activateEnemyNodeAbilityIds": [],
          "m_deactivateEnemyNodeAbilityIds": []
        },
        {
          "m_pos": {
            "x": 99.23077,
            "y": 516.9232
          },
          "m_tag": "",
          "m_warp": 0,
          "m_wait": 0,
          "m_speed_scale": 0,
          "m_activateEnemyNodeAbilityIds": [],
          "m_deactivateEnemyNodeAbilityIds": []
        },
        {
          "m_pos": {
            "x": -45.384644,
            "y": 469.23083
          },
          "m_tag": "",
          "m_warp": 0,
          "m_wait": 0,
          "m_speed_scale": 0,
          "m_activateEnemyNodeAbilityIds": [],
          "m_deactivateEnemyNodeAbilityIds": []
        }
      ]
    },
    {
      "m_routeId": 25,
      "m_omenPos": {
        "x": 0.0,
        "y": 0.0
      },
      "m_points": [
        {
          "m_pos": {
            "x": 601.5604,
            "y": 747.14734
          },
          "m_tag": "",
          "m_warp": 0,
          "m_wait": 0,
          "m_speed_scale": 0,
          "m_activateEnemyNodeAbilityIds": [],
          "m_deactivateEnemyNodeAbilityIds": []
        },
        {
          "m_pos": {
            "x": 548.46155,
            "y": 570.7693
          },
          "m_tag": "",
          "m_warp": 0,
          "m_wait": 1000,
          "m_speed_scale": 0,
          "m_activateEnemyNodeAbilityIds": [],
          "m_deactivateEnemyNodeAbilityIds": []
        },
        {
          "m_pos": {
            "x": 500.92902,
            "y": 438.54398
          },
          "m_tag": "",
          "m_warp": 0,
          "m_wait": 0,
          "m_speed_scale": 0,
          "m_activateEnemyNodeAbilityIds": [],
          "m_deactivateEnemyNodeAbilityIds": []
        },
        {
          "m_pos": {
            "x": -74.34792,
            "y": 443.57553
          },
          "m_tag": "",
          "m_warp": 0,
          "m_wait": 0,
          "m_speed_scale": 0,
          "m_activateEnemyNodeAbilityIds": [],
          "m_deactivateEnemyNodeAbilityIds": []
        }
      ]
    },
    {
      "m_routeId": 26,
      "m_omenPos": {
        "x": 0.0,
        "y": 0.0
      },
      "m_points": [
        {
          "m_pos": {
            "x": 974.9359,
            "y": 750.171
          },
          "m_tag": "",
          "m_warp": 0,
          "m_wait": 0,
          "m_speed_scale": 0,
          "m_activateEnemyNodeAbilityIds": [],
          "m_deactivateEnemyNodeAbilityIds": []
        },
        {
          "m_pos": {
            "x": 871.53845,
            "y": 575.38464
          },
          "m_tag": "",
          "m_warp": 0,
          "m_wait": 1300,
          "m_speed_scale": 0,
          "m_activateEnemyNodeAbilityIds": [],
          "m_deactivateEnemyNodeAbilityIds": []
        },
        {
          "m_pos": {
            "x": 833.07697,
            "y": 520.0
          },
          "m_tag": "",
          "m_warp": 0,
          "m_wait": 0,
          "m_speed_scale": 0,
          "m_activateEnemyNodeAbilityIds": [],
          "m_deactivateEnemyNodeAbilityIds": []
        },
        {
          "m_pos": {
            "x": 773.07697,
            "y": 430.76926
          },
          "m_tag": "",
          "m_warp": 0,
          "m_wait": 0,
          "m_speed_scale": 0,
          "m_activateEnemyNodeAbilityIds": [],
          "m_deactivateEnemyNodeAbilityIds": []
        },
        {
          "m_pos": {
            "x": -73.076965,
            "y": 424.6154
          },
          "m_tag": "",
          "m_warp": 0,
          "m_wait": 0,
          "m_speed_scale": 0,
          "m_activateEnemyNodeAbilityIds": [],
          "m_deactivateEnemyNodeAbilityIds": []
        }
      ]
    },
    {
      "m_routeId": 27,
      "m_omenPos": {
        "x": 0.0,
        "y": 0.0
      },
      "m_points": [
        {
          "m_pos": {
            "x": 1314.6154,
            "y": 315.3846
          },
          "m_tag": "",
          "m_warp": 0,
          "m_wait": 0,
          "m_speed_scale": 0,
          "m_activateEnemyNodeAbilityIds": [],
          "m_deactivateEnemyNodeAbilityIds": []
        },
        {
          "m_pos": {
            "x": 1191.5385,
            "y": 313.84616
          },
          "m_tag": "",
          "m_warp": 0,
          "m_wait": 0,
          "m_speed_scale": 0,
          "m_activateEnemyNodeAbilityIds": [],
          "m_deactivateEnemyNodeAbilityIds": []
        },
        {
          "m_pos": {
            "x": 989.99994,
            "y": 307.69232
          },
          "m_tag": "",
          "m_warp": 0,
          "m_wait": 800,
          "m_speed_scale": 0,
          "m_activateEnemyNodeAbilityIds": [],
          "m_deactivateEnemyNodeAbilityIds": []
        },
        {
          "m_pos": {
            "x": 933.07697,
            "y": 315.3846
          },
          "m_tag": "",
          "m_warp": 0,
          "m_wait": 0,
          "m_speed_scale": 0,
          "m_activateEnemyNodeAbilityIds": [],
          "m_deactivateEnemyNodeAbilityIds": []
        },
        {
          "m_pos": {
            "x": -54.551315,
            "y": 320.0427
          },
          "m_tag": "",
          "m_warp": 0,
          "m_wait": 0,
          "m_speed_scale": 0,
          "m_activateEnemyNodeAbilityIds": [],
          "m_deactivateEnemyNodeAbilityIds": []
        }
      ]
    },
    {
      "m_routeId": 28,
      "m_omenPos": {
        "x": 0.0,
        "y": 0.0
      },
      "m_points": [
        {
          "m_pos": {
            "x": 974.9359,
            "y": 750.171
          },
          "m_tag": "",
          "m_warp": 0,
          "m_wait": 0,
          "m_speed_scale": 0,
          "m_activateEnemyNodeAbilityIds": [],
          "m_deactivateEnemyNodeAbilityIds": []
        },
        {
          "m_pos": {
            "x": 871.53845,
            "y": 575.38464
          },
          "m_tag": "",
          "m_warp": 0,
          "m_wait": 1500,
          "m_speed_scale": 0,
          "m_activateEnemyNodeAbilityIds": [],
          "m_deactivateEnemyNodeAbilityIds": []
        },
        {
          "m_pos": {
            "x": 833.07697,
            "y": 520.0
          },
          "m_tag": "",
          "m_warp": 0,
          "m_wait": 0,
          "m_speed_scale": 0,
          "m_activateEnemyNodeAbilityIds": [],
          "m_deactivateEnemyNodeAbilityIds": []
        },
        {
          "m_pos": {
            "x": 773.07697,
            "y": 430.76926
          },
          "m_tag": "",
          "m_warp": 0,
          "m_wait": 0,
          "m_speed_scale": 0,
          "m_activateEnemyNodeAbilityIds": [],
          "m_deactivateEnemyNodeAbilityIds": []
        },
        {
          "m_pos": {
            "x": -73.076965,
            "y": 424.6154
          },
          "m_tag": "",
          "m_warp": 0,
          "m_wait": 0,
          "m_speed_scale": 0,
          "m_activateEnemyNodeAbilityIds": [],
          "m_deactivateEnemyNodeAbilityIds": []
        }
      ]
    },
    {
      "m_routeId": 29,
      "m_omenPos": {
        "x": 0.0,
        "y": 0.0
      },
      "m_points": [
        {
          "m_pos": {
            "x": 962.2055,
            "y": 755.83704
          },
          "m_tag": "",
          "m_warp": 0,
          "m_wait": 0,
          "m_speed_scale": 0,
          "m_activateEnemyNodeAbilityIds": [],
          "m_deactivateEnemyNodeAbilityIds": []
        },
        {
          "m_pos": {
            "x": 802.96075,
            "y": 449.9859
          },
          "m_tag": "",
          "m_warp": 0,
          "m_wait": 0,
          "m_speed_scale": 0,
          "m_activateEnemyNodeAbilityIds": [],
          "m_deactivateEnemyNodeAbilityIds": []
        },
        {
          "m_pos": {
            "x": -71.5385,
            "y": 456.9231
          },
          "m_tag": "",
          "m_warp": 0,
          "m_wait": 0,
          "m_speed_scale": 0,
          "m_activateEnemyNodeAbilityIds": [],
          "m_deactivateEnemyNodeAbilityIds": []
        }
      ]
    },
    {
      "m_routeId": 30,
      "m_omenPos": {
        "x": 0.0,
        "y": 0.0
      },
      "m_points": [
        {
          "m_pos": {
            "x": 577.6924,
            "y": 792.30774
          },
          "m_tag": "",
          "m_warp": 0,
          "m_wait": 0,
          "m_speed_scale": 0,
          "m_activateEnemyNodeAbilityIds": [],
          "m_deactivateEnemyNodeAbilityIds": []
        },
        {
          "m_pos": {
            "x": 485.3846,
            "y": 463.07693
          },
          "m_tag": "",
          "m_warp": 0,
          "m_wait": 0,
          "m_speed_scale": 0,
          "m_activateEnemyNodeAbilityIds": [],
          "m_deactivateEnemyNodeAbilityIds": []
        },
        {
          "m_pos": {
            "x": -61.602592,
            "y": 451.6667
          },
          "m_tag": "",
          "m_warp": 0,
          "m_wait": 0,
          "m_speed_scale": 0,
          "m_activateEnemyNodeAbilityIds": [],
          "m_deactivateEnemyNodeAbilityIds": []
        }
      ]
    },
    {
      "m_routeId": 31,
      "m_omenPos": {
        "x": 0.0,
        "y": 0.0
      },
      "m_points": [
        {
          "m_pos": {
            "x": 577.6924,
            "y": 792.30774
          },
          "m_tag": "",
          "m_warp": 0,
          "m_wait": 0,
          "m_speed_scale": 0,
          "m_activateEnemyNodeAbilityIds": [],
          "m_deactivateEnemyNodeAbilityIds": []
        },
        {
          "m_pos": {
            "x": 522.3077,
            "y": 578.46155
          },
          "m_tag": "",
          "m_warp": 0,
          "m_wait": 500,
          "m_speed_scale": 0,
          "m_activateEnemyNodeAbilityIds": [],
          "m_deactivateEnemyNodeAbilityIds": []
        },
        {
          "m_pos": {
            "x": 485.3846,
            "y": 461.53845
          },
          "m_tag": "",
          "m_warp": 0,
          "m_wait": 0,
          "m_speed_scale": 0,
          "m_activateEnemyNodeAbilityIds": [],
          "m_deactivateEnemyNodeAbilityIds": []
        },
        {
          "m_pos": {
            "x": -61.602592,
            "y": 454.01712
          },
          "m_tag": "",
          "m_warp": 0,
          "m_wait": 0,
          "m_speed_scale": 0,
          "m_activateEnemyNodeAbilityIds": [],
          "m_deactivateEnemyNodeAbilityIds": []
        }
      ]
    },
    {
      "m_routeId": 32,
      "m_omenPos": {
        "x": 0.0,
        "y": 0.0
      },
      "m_points": [
        {
          "m_pos": {
            "x": 549.0481,
            "y": -23.674917
          },
          "m_tag": "",
          "m_warp": 0,
          "m_wait": 0,
          "m_speed_scale": 0,
          "m_activateEnemyNodeAbilityIds": [],
          "m_deactivateEnemyNodeAbilityIds": []
        },
        {
          "m_pos": {
            "x": 503.76398,
            "y": 45.089912
          },
          "m_tag": "",
          "m_warp": 0,
          "m_wait": 0,
          "m_speed_scale": 0,
          "m_activateEnemyNodeAbilityIds": [],
          "m_deactivateEnemyNodeAbilityIds": []
        },
        {
          "m_pos": {
            "x": 448.41663,
            "y": 140.68985
          },
          "m_tag": "",
          "m_warp": 0,
          "m_wait": 0,
          "m_speed_scale": 0,
          "m_activateEnemyNodeAbilityIds": [],
          "m_deactivateEnemyNodeAbilityIds": []
        },
        {
          "m_pos": {
            "x": 404.80963,
            "y": 206.10037
          },
          "m_tag": "",
          "m_warp": 0,
          "m_wait": 0,
          "m_speed_scale": 0,
          "m_activateEnemyNodeAbilityIds": [],
          "m_deactivateEnemyNodeAbilityIds": []
        },
        {
          "m_pos": {
            "x": 339.2307,
            "y": 352.30774
          },
          "m_tag": "",
          "m_warp": 0,
          "m_wait": 0,
          "m_speed_scale": 0,
          "m_activateEnemyNodeAbilityIds": [],
          "m_deactivateEnemyNodeAbilityIds": []
        },
        {
          "m_pos": {
            "x": 276.5152,
            "y": 354.28946
          },
          "m_tag": "",
          "m_warp": 0,
          "m_wait": 0,
          "m_speed_scale": 0,
          "m_activateEnemyNodeAbilityIds": [],
          "m_deactivateEnemyNodeAbilityIds": []
        },
        {
          "m_pos": {
            "x": -63.95302,
            "y": 352.9487
          },
          "m_tag": "",
          "m_warp": 0,
          "m_wait": 0,
          "m_speed_scale": 0,
          "m_activateEnemyNodeAbilityIds": [],
          "m_deactivateEnemyNodeAbilityIds": []
        }
      ]
    },
    {
      "m_routeId": 33,
      "m_omenPos": {
        "x": 0.0,
        "y": 0.0
      },
      "m_points": [
        {
          "m_pos": {
            "x": 549.0481,
            "y": -23.674917
          },
          "m_tag": "",
          "m_warp": 0,
          "m_wait": 0,
          "m_speed_scale": 0,
          "m_activateEnemyNodeAbilityIds": [],
          "m_deactivateEnemyNodeAbilityIds": []
        },
        {
          "m_pos": {
            "x": 503.76398,
            "y": 45.089912
          },
          "m_tag": "",
          "m_warp": 0,
          "m_wait": 0,
          "m_speed_scale": 0,
          "m_activateEnemyNodeAbilityIds": [],
          "m_deactivateEnemyNodeAbilityIds": []
        },
        {
          "m_pos": {
            "x": 448.41663,
            "y": 140.68985
          },
          "m_tag": "",
          "m_warp": 0,
          "m_wait": 0,
          "m_speed_scale": 0,
          "m_activateEnemyNodeAbilityIds": [],
          "m_deactivateEnemyNodeAbilityIds": []
        },
        {
          "m_pos": {
            "x": 404.80963,
            "y": 206.10037
          },
          "m_tag": "",
          "m_warp": 0,
          "m_wait": 500,
          "m_speed_scale": 0,
          "m_activateEnemyNodeAbilityIds": [],
          "m_deactivateEnemyNodeAbilityIds": []
        },
        {
          "m_pos": {
            "x": 340.76926,
            "y": 349.23077
          },
          "m_tag": "",
          "m_warp": 0,
          "m_wait": 0,
          "m_speed_scale": 0,
          "m_activateEnemyNodeAbilityIds": [],
          "m_deactivateEnemyNodeAbilityIds": []
        },
        {
          "m_pos": {
            "x": 276.15384,
            "y": 355.3846
          },
          "m_tag": "",
          "m_warp": 0,
          "m_wait": 0,
          "m_speed_scale": 0,
          "m_activateEnemyNodeAbilityIds": [],
          "m_deactivateEnemyNodeAbilityIds": []
        },
        {
          "m_pos": {
            "x": -63.95302,
            "y": 355.29916
          },
          "m_tag": "",
          "m_warp": 0,
          "m_wait": 0,
          "m_speed_scale": 0,
          "m_activateEnemyNodeAbilityIds": [],
          "m_deactivateEnemyNodeAbilityIds": []
        }
      ]
    }
  ]
}